Workbook

Sheet RESULTADOS MES
A1: PLANTILLA INFORME MES
A3: AREA | C3: RUBRO | D3: RESULTADO MES | H3: ACUMULADO
D4: N° | E4: VALOR | F4: % | G4: PROMEDIO | H4: N° | I4: VALOR | J4: % | K4: PROMEDIO
A5: VENTAS | B5: VENTA | C5: Ventas Procesables | D5: =+Ventas!B2 -> 0 | E5: =+Ventas!C2 -> 0 | F5: =+E5/$E$8 -> #DIV/0! | G5: =+E5/D5 -> #DIV/0! | H5: =+Ventas!D2 -> 0 | I5: =+Ventas!E2 -> 0 | J5: =+I5/$I$8 -> #DIV/0! | K5: =+I5/H5 -> #DIV/0!
C6: Ventas No Procesables con Rcdo | D6: =+Ventas!B3 -> 0 | E6: =+Ventas!C3 -> 0 | F6: =+E6/$E$8 -> #DIV/0! | G6: =+E6/D6 -> #DIV/0! | H6: =+Ventas!D3 -> 0 | I6: =+Ventas!E3 -> 0 | J6: =+I6/$I$8 -> #DIV/0! | K6: =+I6/H6 -> #DIV/0!
C7: Ventas No Procesables sin Recaudo | D7: =+Ventas!B4 -> 0 | E7: =+Ventas!C4 -> 0 | F7: =+E7/$E$8 -> #DIV/0! | G7: =+E7/D7 -> #DIV/0! | H7: =+Ventas!D4 -> 0 | I7: =+Ventas!E4 -> 0 | J7: =+I7/$I$8 -> #DIV/0! | K7: =+I7/H7 -> #DIV/0!
C8: TOTAL VENTAS DEL MES | D8: =SUM(D5:D7) -> 0 | E8: =SUM(E5:E7) -> 0 | F8: =SUM(F5:F7) -> #DIV/0! | G8: =+E8/D8 -> #DIV/0! | H8: =SUM(H5:H7) -> 0 | I8: =SUM(I5:I7) -> 0 | J8: =SUM(J5:J7) -> #DIV/0! | K8: =+I8/H8 -> #DIV/0!
B9: RECAUDO | C9: RECAUDOS | D9: N° | E9: VALOR | F9: % | G9: % DE VENTAS | H9: N° | I9: VALOR | J9: % | K9: % DE VENTAS
C10: Plata en Mesa | D10: =+Ventas!B5 -> 0 | E10: =+Ventas!C5 -> 0 | F10: =+E10/$E$12 -> #DIV/0! | G10: =+E10/E5 -> #DIV/0! | H10: =+Ventas!D5 -> 0 | I10: =+Ventas!E5 -> 0 | J10: =+I10/$I$12 -> #DIV/0! | K10: =+I10/I8 -> #DIV/0!
C11: Plata en Mes | D11: =+Ventas!B6 -> 0 | E11: =+Ventas!C6 -> 0 | F11: =+E11/$E$12 -> #DIV/0! | G11: =+E11/E5 -> #DIV/0! | H11: =+Ventas!D6 -> 0 | I11: =+Ventas!E6 -> 0 | J11: =+I11/$I$12 -> #DIV/0! | K11: =+I11/I8 -> #DIV/0!
C12: Recaudo por ventas del mes | D12: =+Ventas!B7 -> 0 | E12: =+Ventas!C7 -> 0 | F12: =+E12/$E$12 -> #DIV/0! | G12: =+E12/E5 -> #DIV/0! | H12: =+Ventas!D7 -> 0 | I12: =SUM(I9:I11) -> 0 | J12: =SUM(J9:J11) -> #DIV/0! | K12: =+I12/I8 -> #DIV/0!
B13: TOTALES | C13: ADJUDICACIONES | D13: N° | E13: VALOR | F13: % | G13: PROMEDIO | H13: N° | I13: VALOR | J13: % | K13: PROMEDIO
C14: Ventas | D14: =+D8 -> 0 | E14: =+E8 -> 0 | F14: =+D14/$D$17 -> #DIV/0! | G14: =+E14/D14 -> #DIV/0! | H14: =+H8 -> 0 | I14: =+I8 -> 0 | J14: =+H14/$H$17 -> #DIV/0! | K14: =+I14/H14 -> #DIV/0!
C15: Novaciones | D15: =+Ventas!B9 -> 0 | E15: =+Ventas!C9 -> 0 | F15: =+D15/$D$17 -> #DIV/0! | G15: =+E15/D15 -> #DIV/0! | H15: =+Ventas!D9 -> 0 | I15: =+Ventas!E9 -> 0 | J15: =+H15/$H$17 -> #DIV/0! | K15: =+I15/H15 -> #DIV/0!
C16: Canjes | D16: =+Ventas!B10 -> 0 | E16: =+Ventas!C10 -> 0 | F16: =+D16/$D$17 -> #DIV/0! | G16: =+E16/D16 -> #DIV/0! | H16: =+Ventas!D10 -> 0 | I16: =+Ventas!E10 -> 0 | J16: =+H16/$H$17 -> #DIV/0! | K16: =+I16/H16 -> #DIV/0!
C17: TOTAL ADJUDICACIONES | D17: =+D8+D15+D16 -> 0 | E17: =+E8+E18+E15+E16 -> 0 | F17: =+SUM(F14:F16) -> #DIV/0! | G17: =+E17/D17 -> #DIV/0! | H17: =+H8+H15+H16 -> 0 | I17: =+I8+I18+I15+I16 -> 0 | J17: =+SUM(J14:J16) -> #DIV/0! | K17: =+I17/H17 -> #DIV/0!
C18: Desistidos | D18: =+Ventas!B8 -> 0 | E18: =+Ventas!C8 -> 0 | F18: =+D18/($D$17+D18) -> #DIV/0! | G18: =+E18/D18 -> #DIV/0! | H18: =+Ventas!D8 -> 0 | I18: =+Ventas!E8 -> 0 | J18: =+H18/($H$17+H18) -> #DIV/0! | K18: =+I18/H18 -> #DIV/0!
A19: CARTERA | B19: CARTERA COMERCIAL | D19: MES ACTUAL | F19: RECAUDO | H19: CUMPLIMIENTO | J19: SIGUIENTE MES
D20: N° | E20: VALOR | F20: N° | G20: VALOR | H20: N° | I20: VALOR | J20: N° | K20: VALOR
C21: Del mes | D21: =+COUNTIFS(Cartera!E:E,"Comercial",Cartera!F:F,'RESULTADOS MES'!C23,Cartera!G:G,">0") -> 0 | E21: =SUMIFS(Cartera!G:G,Cartera!E:E,"Comercial",Cartera!F:F,'RESULTADOS MES'!C23,Cartera!G:G,">0") -> 0 | F21: =+COUNTIFS(Cartera!E:E,"Comercial",Cartera!F:F,'RESULTADOS MES'!C23,Cartera!H:H,">0") -> 0 | G21: =+SUMIFS(Cartera!H:H,Cartera!E:E,"Comercial",Cartera!F:F,'RESULTADOS MES'!C23,Cartera!H:H,">0") -> 0 | H21: =+F21/D21 -> #DIV/0! | I21: =+G21/E21 -> #DIV/0! | J21: =COUNTIFS(PptoSiguiente!E:E,"Comercial",PptoSiguiente!F:F,'RESULTADOS MES'!C23,PptoSiguiente!G:G,">0") -> 0 | K21: =SUMIFS(PptoSiguiente!G:G,PptoSiguiente!E:E,"Comercial",PptoSiguiente!F:F,'RESULTADOS MES'!C23,PptoSiguiente!G:G,">0") -> 0
C22: Vencido | D22: =+COUNTIFS(Cartera!E:E,"Comercial",Cartera!F:F,'RESULTADOS MES'!C23,Cartera!I:I,">0") -> 0 | E22: =SUMIFS(Cartera!I:I,Cartera!E:E,"Comercial",Cartera!F:F,'RESULTADOS MES'!C23,Cartera!I:I,">0") -> 0 | F22: =+COUNTIFS(Cartera!E:E,"Comercial",Cartera!F:F,'RESULTADOS MES'!C23,Cartera!J:J,">0") -> 0 | G22: =+SUMIFS(Cartera!J:J,Cartera!E:E,"Comercial",Cartera!F:F,'RESULTADOS MES'!C23,Cartera!J:J,">0") -> 0 | H22: =+F22/D22 -> #DIV/0! | I22: =+G22/E22 -> #DIV/0! | J22: =+COUNTIFS(PptoSiguiente!E:E,"Comercial",PptoSiguiente!F:F,'RESULTADOS MES'!C23,PptoSiguiente!I:I,">0") -> 0 | K22: =SUMIFS(PptoSiguiente!I:I,PptoSiguiente!E:E,"Comercial",PptoSiguiente!F:F,'RESULTADOS MES'!C23,PptoSiguiente!I:I,">0") -> 0
C23: -30-30 | D23: =+COUNTIFS(Cartera!E:E,"Comercial",Cartera!F:F,'RESULTADOS MES'!C23,Cartera!K:K,">0") -> 0 | E23: =+SUBTOTAL(9,E21:E22) -> 0 | F23: =+COUNTIFS(Cartera!E:E,"Comercial",Cartera!F:F,'RESULTADOS MES'!C23,Cartera!L:L,">0") -> 0 | G23: =+SUBTOTAL(9,G21:G22) -> 0 | H23: =+F23/D23 -> #DIV/0! | I23: =+G23/E23 -> #DIV/0! | J23: =+COUNTIFS(PptoSiguiente!E:E,"Comercial",PptoSiguiente!F:F,'RESULTADOS MES'!C23,PptoSiguiente!K:K,">0") -> 0 | K23: =+SUBTOTAL(9,K21:K22) -> 0
C24: Del mes | D24: =+COUNTIFS(Cartera!E:E,"Comercial",Cartera!F:F,'RESULTADOS MES'!C26,Cartera!G:G,">0") -> 0 | E24: =SUMIFS(Cartera!G:G,Cartera!E:E,"Comercial",Cartera!F:F,'RESULTADOS MES'!C26,Cartera!G:G,">0") -> 0 | F24: =+COUNTIFS(Cartera!E:E,"Comercial",Cartera!F:F,'RESULTADOS MES'!C26,Cartera!H:H,">0") -> 0 | G24: =+SUMIFS(Cartera!H:H,Cartera!E:E,"Comercial",Cartera!F:F,'RESULTADOS MES'!C26,Cartera!H:H,">0") -> 0 | H24: =+F24/D24 -> #DIV/0! | I24: =+G24/E24 -> #DIV/0! | J24: =+COUNTIFS(PptoSiguiente!E:E,"Comercial",PptoSiguiente!F:F,'RESULTADOS MES'!C26,PptoSiguiente!G:G,">0") -> 0 | K24: =SUMIFS(PptoSiguiente!G:G,PptoSiguiente!E:E,"Comercial",PptoSiguiente!F:F,'RESULTADOS MES'!C26,PptoSiguiente!G:G,">0") -> 0
C25: Vencido | D25: =+COUNTIFS(Cartera!E:E,"Comercial",Cartera!F:F,'RESULTADOS MES'!C26,Cartera!I:I,">0") -> 0 | E25: =SUMIFS(Cartera!I:I,Cartera!E:E,"Comercial",Cartera!F:F,'RESULTADOS MES'!C26,Cartera!I:I,">0") -> 0 | F25: =+COUNTIFS(Cartera!E:E,"Comercial",Cartera!F:F,'RESULTADOS MES'!C26,Cartera!J:J,">0") -> 0 | G25: =+SUMIFS(Cartera!J:J,Cartera!E:E,"Comercial",Cartera!F:F,'RESULTADOS MES'!C26,Cartera!J:J,">0") -> 0 | H25: =+F25/D25 -> #DIV/0! | I25: =+G25/E25 -> #DIV/0! | J25: =+COUNTIFS(PptoSiguiente!E:E,"Comercial",PptoSiguiente!F:F,'RESULTADOS MES'!C26,PptoSiguiente!I:I,">0") -> 0 | K25: =SUMIFS(PptoSiguiente!I:I,PptoSiguiente!E:E,"Comercial",PptoSiguiente!F:F,'RESULTADOS MES'!C26,PptoSiguiente!I:I,">0") -> 0
C26: 30-60 | D26: =+COUNTIFS(Cartera!E:E,"Comercial",Cartera!F:F,'RESULTADOS MES'!C26,Cartera!K:K,">0") -> 0 | E26: =+SUBTOTAL(9,E24:E25) -> 0 | F26: =+COUNTIFS(Cartera!E:E,"Comercial",Cartera!F:F,'RESULTADOS MES'!C26,Cartera!L:L,">0") -> 0 | G26: =+SUBTOTAL(9,G24:G25) -> 0 | H26: =+F26/D26 -> #DIV/0! | I26: =+G26/E26 -> #DIV/0! | J26: =+COUNTIFS(PptoSiguiente!E:E,"Comercial",PptoSiguiente!F:F,'RESULTADOS MES'!C26,PptoSiguiente!K:K,">0") -> 0 | K26: =+SUBTOTAL(9,K24:K25) -> 0
C27: Del mes | D27: =+COUNTIFS(Cartera!E:E,"Comercial",Cartera!F:F,'RESULTADOS MES'!C29,Cartera!G:G,">0",Cartera!C:C,"Aprobado") -> 0 | E27: =SUMIFS(Cartera!G:G,Cartera!E:E,"Comercial",Cartera!F:F,'RESULTADOS MES'!C29,Cartera!G:G,">0",Cartera!C:C,"Aprobado") -> 0 | F27: =+COUNTIFS(Cartera!E:E,"Comercial",Cartera!F:F,'RESULTADOS MES'!C29,Cartera!H:H,">0",Cartera!C:C,"Aprobado") -> 0 | G27: =+SUMIFS(Cartera!H:H,Cartera!E:E,"Comercial",Cartera!F:F,'RESULTADOS MES'!C29,Cartera!H:H,">0",Cartera!C:C,"Aprobado") -> 0 | H27: =+F27/D27 -> #DIV/0! | I27: =+G27/E27 -> #DIV/0! | J27: =+COUNTIFS(PptoSiguiente!E:E,"Comercial",PptoSiguiente!F:F,'RESULTADOS MES'!C29,PptoSiguiente!G:G,">0",Cartera!C:C,"Aprobado") -> 0 | K27: =SUMIFS(PptoSiguiente!G:G,PptoSiguiente!E:E,"Comercial",PptoSiguiente!F:F,'RESULTADOS MES'!C29,PptoSiguiente!G:G,">0",Cartera!C:C,"Aprobado") -> 0
C28: Vencido | D28: =+COUNTIFS(Cartera!E:E,"Comercial",Cartera!F:F,'RESULTADOS MES'!C29,Cartera!I:I,">0",Cartera!C:C,"Aprobado") -> 0 | E28: =SUMIFS(Cartera!I:I,Cartera!E:E,"Comercial",Cartera!F:F,'RESULTADOS MES'!C29,Cartera!I:I,">0",Cartera!C:C,"Aprobado") -> 0 | F28: =+COUNTIFS(Cartera!E:E,"Comercial",Cartera!F:F,'RESULTADOS MES'!C29,Cartera!J:J,">0",Cartera!C:C,"Aprobado") -> 0 | G28: =+SUMIFS(Cartera!J:J,Cartera!E:E,"Comercial",Cartera!F:F,'RESULTADOS MES'!C29,Cartera!J:J,">0",Cartera!C:C,"Aprobado") -> 0 | H28: =+F28/D28 -> #DIV/0! | I28: =+G28/E28 -> #DIV/0! | J28: =+COUNTIFS(PptoSiguiente!E:E,"Comercial",PptoSiguiente!F:F,'RESULTADOS MES'!C29,PptoSiguiente!I:I,">0",Cartera!C:C,"Aprobado") -> 0 | K28: =SUMIFS(PptoSiguiente!I:I,PptoSiguiente!E:E,"Comercial",PptoSiguiente!F:F,'RESULTADOS MES'!C29,PptoSiguiente!I:I,">0",Cartera!C:C,"Aprobado") -> 0
C29: Prejuridico | D29: =+COUNTIFS(Cartera!E:E,"Comercial",Cartera!F:F,'RESULTADOS MES'!C29,Cartera!K:K,">0",Cartera!C:C,"Aprobado") -> 0 | E29: =+SUBTOTAL(9,E27:E28) -> 0 | F29: =+COUNTIFS(Cartera!E:E,"Comercial",Cartera!F:F,'RESULTADOS MES'!C29,Cartera!L:L,">0",Cartera!C:C,"Aprobado") -> 0 | G29: =+SUBTOTAL(9,G27:G28) -> 0 | H29: =+F29/D29 -> #DIV/0! | I29: =+G29/E29 -> #DIV/0! | J29: =+COUNTIFS(PptoSiguiente!E:E,"Comercial",PptoSiguiente!F:F,'RESULTADOS MES'!C29,PptoSiguiente!K:K,">0",Cartera!C:C,"Aprobado") -> 0 | K29: =+SUBTOTAL(9,K27:K28) -> 0
C30: Del mes | D30: =+COUNTIFS(Cartera!E:E,"Comercial",Cartera!F:F,"Juridico",Cartera!G:G,">0",Cartera!C:C,"Aprobado") -> 0 | E30: =+SUMIFS(Cartera!G:G,Cartera!E:E,"Comercial",Cartera!F:F,"Juridico",Cartera!G:G,">0",Cartera!C:C,"Aprobado") -> 0 | F30: =+COUNTIFS(Cartera!E:E,"Comercial",Cartera!F:F,"Juridico",Cartera!H:H,">0",Cartera!C:C,"Aprobado") -> 0 | G30: =+SUMIFS(Cartera!H:H,Cartera!E:E,"Comercial",Cartera!F:F,"Juridico",Cartera!H:H,">0",Cartera!C:C,"Aprobado") -> 0 | H30: =+F30/D30 -> #DIV/0! | I30: =+G30/E30 -> #DIV/0! | J30: =+COUNTIFS(PptoSiguiente!E:E,"Comercial",PptoSiguiente!F:F,"Juridico",PptoSiguiente!G:G,">0",PptoSiguiente!C:C,"Aprobado") -> 0 | K30: =+SUMIFS(PptoSiguiente!G:G,PptoSiguiente!E:E,"Comercial",PptoSiguiente!F:F,"Juridico",PptoSiguiente!G:G,">0",Cartera!C:C,"Aprobado") -> 0
C31: Vencido | D31: =+COUNTIFS(Cartera!E:E,"Comercial",Cartera!F:F,"Juridico",Cartera!I:I,">0",Cartera!C:C,"Aprobado") -> 0 | E31: =+SUMIFS(Cartera!I:I,Cartera!E:E,"Comercial",Cartera!F:F,"Juridico",Cartera!I:I,">0",Cartera!C:C,"Aprobado") -> 0 | F31: =+COUNTIFS(Cartera!E:E,"Comercial",Cartera!F:F,"Juridico",Cartera!J:J,">0",Cartera!C:C,"Aprobado") -> 0 | G31: =+SUMIFS(Cartera!J:J,Cartera!E:E,"Comercial",Cartera!F:F,"Juridico",Cartera!J:J,">0",Cartera!C:C,"Aprobado") -> 0 | H31: =+F31/D31 -> #DIV/0! | I31: =+G31/E31 -> #DIV/0! | J31: =+COUNTIFS(PptoSiguiente!E:E,"Comercial",PptoSiguiente!F:F,"Juridico",PptoSiguiente!I:I,">0",PptoSiguiente!C:C,"Aprobado") -> 0 | K31: =+SUMIFS(PptoSiguiente!I:I,PptoSiguiente!E:E,"Comercial",PptoSiguiente!F:F,"Juridico",PptoSiguiente!I:I,">0",Cartera!C:C,"Aprobado") -> 0
C32: 90+ (Juridico) | D32: =+COUNTIFS(Cartera!E:E,"Comercial",Cartera!F:F,"Juridico",Cartera!K:K,">0",Cartera!C:C,"Aprobado") -> 0 | E32: =+SUBTOTAL(9,E30:E31) -> 0 | F32: =+COUNTIFS(Cartera!E:E,"Comercial",Cartera!F:F,"Juridico",Cartera!L:L,">0",Cartera!C:C,"Aprobado") -> 0 | G32: =+SUBTOTAL(9,G30:G31) -> 0 | H32: =+F32/D32 -> #DIV/0! | I32: =+G32/E32 -> #DIV/0! | J32: =+COUNTIFS(PptoSiguiente!E:E,"Comercial",PptoSiguiente!F:F,"Juridico",PptoSiguiente!K:K,">0",PptoSiguiente!C:C,"Aprobado") -> 0 | K32: =+SUBTOTAL(9,K30:K31) -> 0
C33: TOTAL PRESUPUESTADO | D33: =+D23+D26+D29+D32 -> 0 | E33: =+SUBTOTAL(9,E21:E32) -> 0 | F33: =+F23+F26+F29+F32 -> 0 | G33: =+SUBTOTAL(9,G21:G32) -> 0 | H33: =+F33/D33 -> #DIV/0! | I33: =+G33/E33 -> #DIV/0! | J33: =+J23+J26+J29 -> 0 | K33: =+SUBTOTAL(9,K21:K29) -> 0
C34: RECAUDO PRESUPUESTADO | D34: =+G33 -> 0 | F34: =+D34/D36 -> #DIV/0!
C35: RECAUDO NO PRESUPUESTADO | D35: =+SUMIFS(Cartera!M:M,Cartera!E:E,"Comercial") -> 0 | F35: =+D35/D36 -> #DIV/0!
C36: TOTAL RECAUDO COMERCIAL | D36: =+D35+G33 -> 0 | F36: =+F34+F35 -> #DIV/0! | G36: TOTAL RECAUDO COMERCIAL ACUMULADO | J36: =+SUMIFS(CarteraHistorico!N:N,CarteraHistorico!E:E,"Comercial") -> 0
B37: CARTERA ADMINISTRATIVA | D37: MES | F37: RECAUDO | H37: CUMPLIMIENTO | J37: SIGUIENTE MES
D38: N° | E38: VALOR | F38: N° | G38: VALOR | H38: N° | I38: VALOR | J38: N° | K38: VALOR
C39: Del mes | D39: =+COUNTIFS(Cartera!E:E,"Administrativa",Cartera!F:F,'RESULTADOS MES'!C41,Cartera!G:G,">0") -> 0 | E39: =SUMIFS(Cartera!G:G,Cartera!E:E,"Administrativa",Cartera!F:F,'RESULTADOS MES'!C41,Cartera!G:G,">0") -> 0 | F39: =+COUNTIFS(Cartera!E:E,"Administrativa",Cartera!F:F,'RESULTADOS MES'!C41,Cartera!H:H,">0") -> 0 | G39: =+SUMIFS(Cartera!H:H,Cartera!E:E,"Administrativa",Cartera!F:F,'RESULTADOS MES'!C41) -> 0 | H39: =+F39/D39 -> #DIV/0! | I39: =+G39/E39 -> #DIV/0! | J39: =COUNTIFS(PptoSiguiente!E:E,"Administrativa",PptoSiguiente!F:F,'RESULTADOS MES'!C41,PptoSiguiente!G:G,">0") -> 0 | K39: =SUMIFS(PptoSiguiente!G:G,PptoSiguiente!E:E,"Administrativa",PptoSiguiente!F:F,'RESULTADOS MES'!C41,PptoSiguiente!G:G,">0") -> 0
C40: Vencido | D40: =+COUNTIFS(Cartera!E:E,"Administrativa",Cartera!F:F,'RESULTADOS MES'!C41,Cartera!I:I,">0") -> 0 | E40: =SUMIFS(Cartera!I:I,Cartera!E:E,"Administrativa",Cartera!F:F,'RESULTADOS MES'!C41,Cartera!I:I,">0") -> 0 | F40: =+COUNTIFS(Cartera!E:E,"Administrativa",Cartera!F:F,'RESULTADOS MES'!C41,Cartera!J:J,">0") -> 0 | G40: =+SUMIFS(Cartera!J:J,Cartera!E:E,"Administrativa",Cartera!F:F,'RESULTADOS MES'!C41) -> 0 | H40: =+F40/D40 -> #DIV/0! | I40: =+G40/E40 -> #DIV/0! | J40: =+COUNTIFS(PptoSiguiente!E:E,"Administrativa",PptoSiguiente!F:F,'RESULTADOS MES'!C41,PptoSiguiente!I:I,">0") -> 0 | K40: =SUMIFS(PptoSiguiente!I:I,PptoSiguiente!E:E,"Administrativa",PptoSiguiente!F:F,'RESULTADOS MES'!C41,PptoSiguiente!I:I,">0") -> 0
C41: -30-30 | D41: =+COUNTIFS(Cartera!E:E,"Administrativa",Cartera!F:F,'RESULTADOS MES'!C41,Cartera!K:K,">0") -> 0 | E41: =+SUBTOTAL(9,E39:E40) -> 0 | F41: =+COUNTIFS(Cartera!E:E,"Administrativa",Cartera!F:F,'RESULTADOS MES'!C41,Cartera!L:L,">0") -> 0 | G41: =+SUBTOTAL(9,G39:G40) -> 0 | H41: =+F41/D41 -> #DIV/0! | I41: =+G41/E41 -> #DIV/0! | J41: =+COUNTIFS(PptoSiguiente!E:E,"Administrativa",PptoSiguiente!F:F,'RESULTADOS MES'!C41,PptoSiguiente!K:K,">0") -> 0 | K41: =+SUBTOTAL(9,K39:K40) -> 0
C42: Del mes | D42: =+COUNTIFS(Cartera!E:E,"Administrativa",Cartera!F:F,'RESULTADOS MES'!C44,Cartera!G:G,">0") -> 0 | E42: =SUMIFS(Cartera!G:G,Cartera!E:E,"Administrativa",Cartera!F:F,'RESULTADOS MES'!C44,Cartera!G:G,">0") -> 0 | F42: =+COUNTIFS(Cartera!E:E,"Administrativa",Cartera!F:F,'RESULTADOS MES'!C44,Cartera!H:H,">0") -> 0 | G42: =+SUMIFS(Cartera!H:H,Cartera!E:E,"Administrativa",Cartera!F:F,'RESULTADOS MES'!C44) -> 0 | H42: =+F42/D42 -> #DIV/0! | I42: =+G42/E42 -> #DIV/0! | J42: =+COUNTIFS(PptoSiguiente!E:E,"Administrativa",PptoSiguiente!F:F,'RESULTADOS MES'!C44,PptoSiguiente!G:G,">0") -> 0 | K42: =SUMIFS(PptoSiguiente!G:G,PptoSiguiente!E:E,"Administrativa",PptoSiguiente!F:F,'RESULTADOS MES'!C44,PptoSiguiente!G:G,">0") -> 0
C43: Vencido | D43: =+COUNTIFS(Cartera!E:E,"Administrativa",Cartera!F:F,'RESULTADOS MES'!C44,Cartera!I:I,">0") -> 0 | E43: =SUMIFS(Cartera!I:I,Cartera!E:E,"Administrativa",Cartera!F:F,'RESULTADOS MES'!C44,Cartera!I:I,">0") -> 0 | F43: =+COUNTIFS(Cartera!E:E,"Administrativa",Cartera!F:F,'RESULTADOS MES'!C44,Cartera!J:J,">0") -> 0 | G43: =+SUMIFS(Cartera!J:J,Cartera!E:E,"Administrativa",Cartera!F:F,'RESULTADOS MES'!C44) -> 0 | H43: =+F43/D43 -> #DIV/0! | I43: =+G43/E43 -> #DIV/0! | J43: =+COUNTIFS(PptoSiguiente!E:E,"Administrativa",PptoSiguiente!F:F,'RESULTADOS MES'!C44,PptoSiguiente!I:I,">0") -> 0 | K43: =SUMIFS(PptoSiguiente!I:I,PptoSiguiente!E:E,"Administrativa",PptoSiguiente!F:F,'RESULTADOS MES'!C44,PptoSiguiente!I:I,">0") -> 0
C44: 30-60 | D44: =+COUNTIFS(Cartera!E:E,"Administrativa",Cartera!F:F,'RESULTADOS MES'!C44,Cartera!K:K,">0") -> 0 | E44: =+SUBTOTAL(9,E42:E43) -> 0 | F44: =+COUNTIFS(Cartera!E:E,"Administrativa",Cartera!F:F,'RESULTADOS MES'!C44,Cartera!L:L,">0") -> 0 | G44: =+SUBTOTAL(9,G42:G43) -> 0 | H44: =+F44/D44 -> #DIV/0! | I44: =+G44/E44 -> #DIV/0! | J44: =+COUNTIFS(PptoSiguiente!E:E,"Administrativa",PptoSiguiente!F:F,'RESULTADOS MES'!C44,PptoSiguiente!K:K,">0") -> 0 | K44: =+SUBTOTAL(9,K42:K43) -> 0
C45: Del mes | D45: =+COUNTIFS(Cartera!E:E,"Administrativa",Cartera!F:F,'RESULTADOS MES'!C47,Cartera!G:G,">0") -> 0 | E45: =SUMIFS(Cartera!G:G,Cartera!E:E,"Administrativa",Cartera!F:F,'RESULTADOS MES'!C47,Cartera!G:G,">0") -> 0 | F45: =+COUNTIFS(Cartera!E:E,"Administrativa",Cartera!F:F,'RESULTADOS MES'!C47,Cartera!H:H,">0") -> 0 | G45: =+SUMIFS(Cartera!H:H,Cartera!E:E,"Administrativa",Cartera!F:F,'RESULTADOS MES'!C47) -> 0 | H45: =+F45/D45 -> #DIV/0! | I45: =+G45/E45 -> #DIV/0! | J45: =+COUNTIFS(PptoSiguiente!E:E,"Administrativa",PptoSiguiente!F:F,'RESULTADOS MES'!C47,PptoSiguiente!G:G,">0") -> 0 | K45: =SUMIFS(PptoSiguiente!G:G,PptoSiguiente!E:E,"Administrativa",PptoSiguiente!F:F,'RESULTADOS MES'!C47,PptoSiguiente!G:G,">0") -> 0
C46: Vencido | D46: =+COUNTIFS(Cartera!E:E,"Administrativa",Cartera!F:F,'RESULTADOS MES'!C47,Cartera!I:I,">0") -> 0 | E46: =SUMIFS(Cartera!I:I,Cartera!E:E,"Administrativa",Cartera!F:F,'RESULTADOS MES'!C47,Cartera!I:I,">0") -> 0 | F46: =+COUNTIFS(Cartera!E:E,"Administrativa",Cartera!F:F,'RESULTADOS MES'!C47,Cartera!J:J,">0") -> 0 | G46: =+SUMIFS(Cartera!J:J,Cartera!E:E,"Administrativa",Cartera!F:F,'RESULTADOS MES'!C47) -> 0 | H46: =+F46/D46 -> #DIV/0! | I46: =+G46/E46 -> #DIV/0! | J46: =+COUNTIFS(PptoSiguiente!E:E,"Administrativa",PptoSiguiente!F:F,'RESULTADOS MES'!C47,PptoSiguiente!I:I,">0") -> 0 | K46: =SUMIFS(PptoSiguiente!I:I,PptoSiguiente!E:E,"Administrativa",PptoSiguiente!F:F,'RESULTADOS MES'!C47,PptoSiguiente!I:I,">0") -> 0
C47: Prejuridico | D47: =+COUNTIFS(Cartera!E:E,"Administrativa",Cartera!F:F,'RESULTADOS MES'!C47,Cartera!K:K,">0") -> 0 | E47: =+SUBTOTAL(9,E45:E46) -> 0 | F47: =+COUNTIFS(Cartera!E:E,"Administrativa",Cartera!F:F,'RESULTADOS MES'!C47,Cartera!L:L,">0") -> 0 | G47: =+SUBTOTAL(9,G45:G46) -> 0 | H47: =+F47/D47 -> #DIV/0! | I47: =+G47/E47 -> #DIV/0! | J47: =+COUNTIFS(PptoSiguiente!E:E,"Administrativa",PptoSiguiente!F:F,'RESULTADOS MES'!C47,PptoSiguiente!K:K,">0") -> 0 | K47: =+SUBTOTAL(9,K45:K46) -> 0
C48: TOTAL PRESUPUESTADO | D48: =+D41+D44+D47 -> 0 | E48: =+SUBTOTAL(9,E39:E47) -> 0 | F48: =+F41+F44+F47 -> 0 | G48: =+SUBTOTAL(9,G39:G47) -> 0 | H48: =+F48/D48 -> #DIV/0! | I48: =+G48/E48 -> #DIV/0! | J48: =+J41+J44+J47 -> 0 | K48: =+SUBTOTAL(9,K39:K47) -> 0
C49: RECAUDO PRESUPUESTADO | D49: =+G48 -> 0 | F49: =+D49/D51 -> #DIV/0!
C50: RECAUDO NO PRESUPUESTADO | D50: =+SUMIFS(Cartera!M:M,Cartera!E:E,"Administrativa",Cartera!F:F,"<>Juridico") -> 0 | F50: =+D50/D51 -> #DIV/0!
C51: TOTAL RECAUDO Administrativo | D51: =+D50+G48 -> 0 | F51: =+F49+F50 -> #DIV/0! | G51: TOTAL RECAUDO ADMIN ACUMULADO | J51: =+SUMIFS(CarteraHistorico!N:N,CarteraHistorico!E:E,"Administrativa") -> 0
B52: CARTERA JURIDICA | D52: MES | F52: RECAUDO | H52: CUMPLIMIENTO | J52: SIGUIENTE MES
D53: N° | E53: VALOR | F53: N° | G53: VALOR | H53: N° | I53: VALOR | J53: N° | K53: VALOR
C54: Del mes | D54: =+COUNTIFS(Cartera!E:E,"Comercial",Cartera!G:G,">0",Cartera!C:C,"Juridico") -> 0 | E54: =+SUMIFS(Cartera!G:G,Cartera!E:E,"Comercial",Cartera!G:G,">0",Cartera!C:C,"Juridico") -> 0 | F54: =+COUNTIFS(Cartera!E:E,"Comercial",Cartera!G:G,">0",Cartera!H:H,">0",Cartera!C:C,"Juridico") -> 0 | G54: =+SUMIFS(Cartera!H:H,Cartera!E:E,"Comercial",Cartera!G:G,">0",Cartera!H:H,">0",Cartera!C:C,"Juridico") -> 0 | H54: =+F54/D54 -> #DIV/0! | I54: =+G54/E54 -> #DIV/0! | J54: =+COUNTIFS(PptoSiguiente!E:E,"Comercial",PptoSiguiente!G:G,">0",PptoSiguiente!C:C,"Juridico") -> 0 | K54: =+SUMIFS(PptoSiguiente!G:G,PptoSiguiente!E:E,"Comercial",PptoSiguiente!G:G,">0",PptoSiguiente!C:C,"Juridico") -> 0
C55: Vencido | D55: =+COUNTIFS(Cartera!E:E,"Comercial",Cartera!I:I,">0",Cartera!C:C,"Juridico") -> 0 | E55: =+SUMIFS(Cartera!I:I,Cartera!E:E,"Comercial",Cartera!I:I,">0",Cartera!C:C,"Juridico") -> 0 | F55: =+COUNTIFS(Cartera!E:E,"Comercial",Cartera!G:G,">0",Cartera!J:J,">0",Cartera!C:C,"Juridico") -> 0 | G55: =+SUMIFS(Cartera!J:J,Cartera!E:E,"Comercial",Cartera!G:G,">0",Cartera!J:J,">0",Cartera!C:C,"Juridico") -> 0 | H55: =+F55/D55 -> #DIV/0! | I55: =+G55/E55 -> #DIV/0! | J55: =+COUNTIFS(PptoSiguiente!E:E,"Comercial",PptoSiguiente!I:I,">0",PptoSiguiente!C:C,"Juridico") -> 0 | K55: =+SUMIFS(PptoSiguiente!I:I,PptoSiguiente!E:E,"Comercial",PptoSiguiente!I:I,">0",PptoSiguiente!C:C,"Juridico") -> 0
C56: Total Comercial | D56: =+COUNTIFS(Cartera!E:E,"Comercial",Cartera!F:F,"Juridico",Cartera!K:K,">0",Cartera!C:C,"Juridico") -> 0 | E56: =+SUBTOTAL(9,E54:E55) -> 0 | F56: =+COUNTIFS(Cartera!E:E,"Comercial",Cartera!G:G,">0",Cartera!L:L,">0",Cartera!C:C,"Juridico") -> 0 | G56: =+SUBTOTAL(9,G54:G55) -> 0 | H56: =+F56/D56 -> #DIV/0! | I56: =+G56/E56 -> #DIV/0! | J56: =+COUNTIFS(PptoSiguiente!E:E,"Comercial",PptoSiguiente!K:K,">0",PptoSiguiente!C:C,"Juridico") -> 0 | K56: =+SUBTOTAL(9,K54:K55) -> 0
C57: Del mes | D57: =+COUNTIFS(Cartera!E:E,"Administrativa",Cartera!F:F,"Juridico",Cartera!G:G,">0") -> 0 | E57: =+SUMIFS(Cartera!G:G,Cartera!E:E,"Administrativa",Cartera!F:F,"Juridico",Cartera!G:G,">0") -> 0 | F57: =+COUNTIFS(Cartera!E:E,"Administrativa",Cartera!F:F,"Juridico",Cartera!G:G,">0",Cartera!H:H,">0") -> 0 | G57: =+SUMIFS(Cartera!H:H,Cartera!E:E,"Administrativa",Cartera!F:F,"Juridico") -> 0 | H57: =+F57/D57 -> #DIV/0! | I57: =+G57/E57 -> #DIV/0! | J57: =+COUNTIFS(PptoSiguiente!E:E,"Administrativa",PptoSiguiente!F:F,"Juridico",PptoSiguiente!G:G,">0") -> 0 | K57: =+SUMIFS(PptoSiguiente!G:G,PptoSiguiente!E:E,"Administrativa",PptoSiguiente!F:F,"Juridico",PptoSiguiente!G:G,">0") -> 0
C58: Vencido | D58: =+COUNTIFS(Cartera!E:E,"Administrativa",Cartera!F:F,"Juridico",Cartera!I:I,">0") -> 0 | E58: =+SUMIFS(Cartera!I:I,Cartera!E:E,"Administrativa",Cartera!F:F,"Juridico",Cartera!I:I,">0") -> 0 | F58: =+COUNTIFS(Cartera!E:E,"Administrativa",Cartera!F:F,"Juridico",Cartera!G:G,">0",Cartera!J:J,">0") -> 0 | G58: =+SUMIFS(Cartera!J:J,Cartera!E:E,"Administrativa",Cartera!F:F,"Juridico") -> 0 | H58: =+F58/D58 -> #DIV/0! | I58: =+G58/E58 -> #DIV/0! | J58: =+COUNTIFS(PptoSiguiente!E:E,"Administrativa",PptoSiguiente!F:F,"Juridico",PptoSiguiente!I:I,">0") -> 0 | K58: =+SUMIFS(PptoSiguiente!I:I,PptoSiguiente!E:E,"Administrativa",PptoSiguiente!F:F,"Juridico",PptoSiguiente!I:I,">0") -> 0
C59: Total Administrativa | D59: =+COUNTIFS(Cartera!E:E,"Administrativa",Cartera!F:F,"Juridico",Cartera!K:K,">0") -> 0 | E59: =+SUBTOTAL(9,E57:E58) -> 0 | F59: =+COUNTIFS(Cartera!E:E,"Administrativa",Cartera!F:F,"Juridico",Cartera!G:G,">0",Cartera!L:L,">0") -> 0 | G59: =+SUBTOTAL(9,G57:G58) -> 0 | H59: =+F59/D59 -> #DIV/0! | I59: =+G59/E59 -> #DIV/0! | J59: =+COUNTIFS(PptoSiguiente!E:E,"Administrativa",PptoSiguiente!F:F,"Juridico",PptoSiguiente!K:K,">0") -> 0 | K59: =+SUBTOTAL(9,K57:K58) -> 0
C60: TOTAL PRESUPUESTADO | D60: =+D56+D59 -> 0 | E60: =+E56+E59 -> 0 | F60: =+F56+F59 -> 0 | G60: =+G56+G59 -> 0 | H60: =+F60/D60 -> #DIV/0! | I60: =+G60/E60 -> #DIV/0! | J60: =+J56+J59 -> 0 | K60: =+K56+K59 -> 0
C61: RECAUDO PRESUPUESTADO | D61: =+G60 -> 0 | F61: =+D61/D63 -> #DIV/0!
C62: RECAUDO NO PRESUPUESTADO | D62: =+SUMIFS(Cartera!M:M,Cartera!F:F,"Juridico") -> 0 | F62: =+D62/D63 -> #DIV/0!
C63: TOTAL RECAUDO Juridico | D63: =+D62+G60 -> 0 | F63: =+F61+F62 -> #DIV/0! | G63: TOTAL RECAUDO JURIDICO ACUMULADO | J63: =+SUMIFS(CarteraHistorico!N:N,CarteraHistorico!E:E,"Juridico") -> 0
A64: TOTAL RECAUDO CARTERA | D64: =+D63+D51+D36 -> 0 | G64: TOTAL RECAUDO CARTERA ACUMULADO | J64: =+J36+J51+J63 -> 0
A65: TOTAL RECAUDO PROYECTO | D65: =+D64+E12 -> 0 | G65: TOTAL RECAUDO PROYECTO | J65: =+J64+I12 -> 0
D66: Ejecutado Mes | G66: % Ventas Total | H66: Acumulado | K66: =+G66 -> % Ventas Total
A67: GASTOS | B67: OPERACIÓN | C67: 35. Masa Salarial | D67: =+SUMIF('Gastos Mes'!G:G,'RESULTADOS MES'!L67,'Gastos Mes'!H:H) -> 0 | G67: =D67/IF($G$66="% presupuesto",F67,VLOOKUP($G$66,Control!F:G,2,FALSE)) -> #DIV/0! | H67: =+SUMIF(GastosHistorico!G:G,'RESULTADOS MES'!L67,GastosHistorico!H:H)+D67 -> 0 | K67: =H67/VLOOKUP($G$66,Control!F:H,3,FALSE) -> #DIV/0! | L67: 35
C68: 36. Arriendos | D68: =+SUMIF('Gastos Mes'!G:G,'RESULTADOS MES'!L68,'Gastos Mes'!H:H) -> 0 | G68: =D68/IF($G$66="% presupuesto",F68,VLOOKUP($G$66,Control!F:G,2,FALSE)) -> #DIV/0! | H68: =+SUMIF(GastosHistorico!G:G,'RESULTADOS MES'!L68,GastosHistorico!H:H)+D68 -> 0 | K68: =H68/VLOOKUP($G$66,Control!F:H,3,FALSE) -> #DIV/0! | L68: 36
C69: 37. Impuestos | D69: =+SUMIF('Gastos Mes'!G:G,'RESULTADOS MES'!L69,'Gastos Mes'!H:H) -> 0 | G69: =D69/IF($G$66="% presupuesto",F69,VLOOKUP($G$66,Control!F:G,2,FALSE)) -> #DIV/0! | H69: =+SUMIF(GastosHistorico!G:G,'RESULTADOS MES'!L69,GastosHistorico!H:H)+D69 -> 0 | K69: =H69/VLOOKUP($G$66,Control!F:H,3,FALSE) -> #DIV/0! | L69: 37
C70: 38. Operación | D70: =+SUMIF('Gastos Mes'!G:G,'RESULTADOS MES'!L70,'Gastos Mes'!H:H) -> 0 | G70: =D70/IF($G$66="% presupuesto",F70,VLOOKUP($G$66,Control!F:G,2,FALSE)) -> #DIV/0! | H70: =+SUMIF(GastosHistorico!G:G,'RESULTADOS MES'!L70,GastosHistorico!H:H)+D70 -> 0 | K70: =H70/VLOOKUP($G$66,Control!F:H,3,FALSE) -> #DIV/0! | L70: 38
C71: 39. Activos | D71: =+SUMIF('Gastos Mes'!G:G,'RESULTADOS MES'!L71,'Gastos Mes'!H:H) -> 0 | G71: =D71/IF($G$66="% presupuesto",F71,VLOOKUP($G$66,Control!F:G,2,FALSE)) -> #DIV/0! | H71: =+SUMIF(GastosHistorico!G:G,'RESULTADOS MES'!L71,GastosHistorico!H:H)+D71 -> 0 | K71: =H71/VLOOKUP($G$66,Control!F:H,3,FALSE) -> #DIV/0! | L71: 39
C72: 40. Mantenimientos y Servicios | D72: =+SUMIF('Gastos Mes'!G:G,'RESULTADOS MES'!L72,'Gastos Mes'!H:H) -> 0 | G72: =D72/IF($G$66="% presupuesto",F72,VLOOKUP($G$66,Control!F:G,2,FALSE)) -> #DIV/0! | H72: =+SUMIF(GastosHistorico!G:G,'RESULTADOS MES'!L72,GastosHistorico!H:H)+D72 -> 0 | K72: =H72/VLOOKUP($G$66,Control!F:H,3,FALSE) -> #DIV/0! | L72: 40
C73: 41. Servicios Publicos | D73: =+SUMIF('Gastos Mes'!G:G,'RESULTADOS MES'!L73,'Gastos Mes'!H:H) -> 0 | G73: =D73/IF($G$66="% presupuesto",F73,VLOOKUP($G$66,Control!F:G,2,FALSE)) -> #DIV/0! | H73: =+SUMIF(GastosHistorico!G:G,'RESULTADOS MES'!L73,GastosHistorico!H:H)+D73 -> 0 | K73: =H73/VLOOKUP($G$66,Control!F:H,3,FALSE) -> #DIV/0! | L73: 41
C74: 42. Internet Y Telefonia | D74: =+SUMIF('Gastos Mes'!G:G,'RESULTADOS MES'!L74,'Gastos Mes'!H:H) -> 0 | G74: =D74/IF($G$66="% presupuesto",F74,VLOOKUP($G$66,Control!F:G,2,FALSE)) -> #DIV/0! | H74: =+SUMIF(GastosHistorico!G:G,'RESULTADOS MES'!L74,GastosHistorico!H:H)+D74 -> 0 | K74: =H74/VLOOKUP($G$66,Control!F:H,3,FALSE) -> #DIV/0! | L74: 42
C75: 43. Seguros | D75: =+SUMIF('Gastos Mes'!G:G,'RESULTADOS MES'!L75,'Gastos Mes'!H:H) -> 0 | G75: =D75/IF($G$66="% presupuesto",F75,VLOOKUP($G$66,Control!F:G,2,FALSE)) -> #DIV/0! | H75: =+SUMIF(GastosHistorico!G:G,'RESULTADOS MES'!L75,GastosHistorico!H:H)+D75 -> 0 | K75: =H75/VLOOKUP($G$66,Control!F:H,3,FALSE) -> #DIV/0! | L75: 43
C76: 44. Gastos Financieros | D76: =+SUMIF('Gastos Mes'!G:G,'RESULTADOS MES'!L76,'Gastos Mes'!H:H) -> 0 | G76: =D76/IF($G$66="% presupuesto",F76,VLOOKUP($G$66,Control!F:G,2,FALSE)) -> #DIV/0! | H76: =+SUMIF(GastosHistorico!G:G,'RESULTADOS MES'!L76,GastosHistorico!H:H)+D76 -> 0 | K76: =H76/VLOOKUP($G$66,Control!F:H,3,FALSE) -> #DIV/0! | L76: 44
C77: 45. Viaticos | D77: =+SUMIF('Gastos Mes'!G:G,'RESULTADOS MES'!L77,'Gastos Mes'!H:H) -> 0 | G77: =D77/IF($G$66="% presupuesto",F77,VLOOKUP($G$66,Control!F:G,2,FALSE)) -> #DIV/0! | H77: =+SUMIF(GastosHistorico!G:G,'RESULTADOS MES'!L77,GastosHistorico!H:H)+D77 -> 0 | K77: =H77/VLOOKUP($G$66,Control!F:H,3,FALSE) -> #DIV/0! | L77: 45
C78: 46. Gastos Legales | D78: =+SUMIF('Gastos Mes'!G:G,'RESULTADOS MES'!L78,'Gastos Mes'!H:H) -> 0 | G78: =D78/IF($G$66="% presupuesto",F78,VLOOKUP($G$66,Control!F:G,2,FALSE)) -> #DIV/0! | H78: =+SUMIF(GastosHistorico!G:G,'RESULTADOS MES'!L78,GastosHistorico!H:H)+D78 -> 0 | K78: =H78/VLOOKUP($G$66,Control!F:H,3,FALSE) -> #DIV/0! | L78: 46
C79: TOTAL OPERACIÓN | D79: =+SUBTOTAL(9,D67:D78) -> 0 | G79: =+SUBTOTAL(9,G67:G78) -> #DIV/0! | H79: =+SUBTOTAL(9,H67:H78) -> 0 | K79: =+SUBTOTAL(9,K67:K78) -> #DIV/0!
B80: TIERRA | C80: 55. Costo Directo | D80: =+SUMIF('Gastos Mes'!G:G,'RESULTADOS MES'!L80,'Gastos Mes'!H:H) -> 0 | G80: =D80/VLOOKUP($G$66,Control!F:G,2,FALSE) -> #DIV/0! | H80: =+SUMIF(GastosHistorico!G:G,'RESULTADOS MES'!L80,GastosHistorico!H:H)+D80 -> 0 | K80: =H80/VLOOKUP($G$66,Control!F:H,3,FALSE) -> #DIV/0! | L80: 55
C81: 56. Rendimientos | D81: =+SUMIF('Gastos Mes'!G:G,'RESULTADOS MES'!L81,'Gastos Mes'!H:H) -> 0 | G81: =D81/VLOOKUP($G$66,Control!F:G,2,FALSE) -> #DIV/0! | H81: =+SUMIF(GastosHistorico!G:G,'RESULTADOS MES'!L81,GastosHistorico!H:H)+D81 -> 0 | K81: =H81/VLOOKUP($G$66,Control!F:H,3,FALSE) -> #DIV/0! | L81: 56
C82: 57. Gastos Legales y de Registro | D82: =+SUMIF('Gastos Mes'!G:G,'RESULTADOS MES'!L82,'Gastos Mes'!H:H) -> 0 | G82: =D82/VLOOKUP($G$66,Control!F:G,2,FALSE) -> #DIV/0! | H82: =+SUMIF(GastosHistorico!G:G,'RESULTADOS MES'!L82,GastosHistorico!H:H)+D82 -> 0 | K82: =H82/VLOOKUP($G$66,Control!F:H,3,FALSE) -> #DIV/0! | L82: 57
C83: TOTAL TIERRAS | D83: =+SUBTOTAL(9,D80:D82) -> 0 | G83: =+SUBTOTAL(9,G80:G82) -> #DIV/0! | H83: =+SUBTOTAL(9,H80:H82) -> 0 | K83: =+SUBTOTAL(9,K80:K82) -> #DIV/0!
B84: TOTAL GASTOS | D84: =+SUBTOTAL(9,D67:D83) -> 0 | G84: =+SUBTOTAL(9,G67:G83) -> #DIV/0! | H84: =+SUBTOTAL(9,H67:H83) -> 0 | K84: =+SUBTOTAL(9,K67:K83) -> #DIV/0!
A85: RESULTADO PERIODO | E85: =+VLOOKUP($G$66,Control!F:G,2,FALSE)-D84 -> 0 | G85: RESULTADO ACUMULADO | J85: =+VLOOKUP($G$66,Control!F:H,3,FALSE)-H84 -> 0

Sheet Ventas
A1: Item | B1: Cantidad Mes | C1: Valor Mes | D1: Cantidad Acum | E1: Valor Acumulado

Sheet Recaudos
A1: Fecha | B1: Adj | C1: Cliente | D1: Inmueble | E1: Valor | F1: Operación | G1: FormaPago

Sheet Detalle Ventas
A1: Fecha | B1: Adj | C1: Nombre | D1: Inmueble | E1: Valor | F1: Base Comision | G1: % Comis Operativa | H1: $ Comis Operativa | I1: $Comis Corporativa | J1: Plata Mesa | K1: Plata Mes

Sheet Cartera
A1: Adjudicacion | B1: Cliente | C1: Estado | D1: Origen | E1: TipoCartera | F1: Edad | G1: pptomes | H1: rcdomes | I1: pptovencido | J1: rcdovencido | K1: pptototal | L1: rcdopptado | M1: rcdonopptado | N1: rcdototal

Sheet CarteraHistorico
A1: Adjudicacion | B1: Cliente | C1: Estado | D1: Origen | E1: TipoCartera | F1: Edad | G1: pptomes | H1: rcdomes | I1: pptovencido | J1: rcdovencido | K1: pptototal | L1: rcdopptado | M1: rcdonopptado | N1: rcdototal | O1: periodo

Sheet PptoSiguiente
A1: Adjudicacion | B1: Cliente | C1: Estado | D1: Origen | E1: TipoCartera | F1: Edad | G1: pptomes | H1: rcdomes | I1: pptovencido | J1: rcdovencido | K1: pptototal | L1: rcdopptado | M1: rcdonopptado | N1: rcdototal

Sheet Gastos Mes
A1: Fecha | B1: Comprobante | C1: Cuenta | D1: Descripcion Cuenta | E1: Tercero | F1: Descripcion Gasto | G1: Item | H1: Valor | I1: Empresa

Sheet Metas
A1: Oficina | B1: Mes | C1: Año | D1: 12 | E1: 13 | F1: 14 | G1: 21 | H1: 22 | I1: 24
D2: Rec.Cuotas Mes Comercial | E2: Rec. Ctas Vencidas Comercial | F2: Rec. Prejudridico Comercial | G2: Rec.Cuotas Mes Admin | H2: Rec. Ctas Vencidas Admin | I2: Rec. Prejudridico Admin
A3: Sandville Beach | B3: 10 | C3: 2018 | D3: 1 | E3: 0.5 | F3: 0.15 | G3: 0.5 | H3: 0.7 | I3: 0.05
A4: Sandville del Sol | B4: 10 | C4: 2018 | D4: 0.5 | E4: 0.7 | F4: 0.1 | G4: 0.5 | H4: 0.8 | I4: 0.1
A5: Sandville del Mar | B5: 10 | C5: 2018 | D5: 0.8 | E5: 0.5 | F5: 0.2 | G5: 0.6 | H5: 0.8 | I5: 0.15
A6: Westville | B6: 10 | C6: 2018 | D6: 0.8 | E6: 0.7 | F6: 0.2 | G6: 0.6 | H6: 0.85 | I6: 0.15

Sheet Hoja2
B1: MONTERIA | C1: SINCELEJO | D1: MEDELLIN | E1: SANDVILLE | F1: WESTVILLE
A2: GASTOS DE NOMINA
A3: 14200101 SUELDOS Y SALARIOS | B3: 8914088 | C3: 741011 | D3: 16946296 | E3: 26601395 | F3: 3320392
A4: 14200107 SUBSIDIO DE TRANSPORTE | B4: 661590 | C4: 82331 | D4: 699815 | E4: 1443736 | F4: 264636
A5: 14200108 AUXILIO DE TRANSPORTE | B5: 0 | C5: 0 | D5: 0 | E5: 0 | F5: 0
A6: 14200109 AUXILIO DE RODAMIENTO | B6: 0 | C6: 0 | D6: 0 | E6: 0 | F6: 0
A7: 14200113 BONIFICACIÓN SALARIAL | B7: 0 | C7: 0 | D7: 0 | E7: 0 | F7: 0
A8: 14200115 BONIFICACION SPIFF | B8: 0 | C8: 0 | D8: 0 | E8: 0 | F8: 0
A9: 14200116 BONIFICACIÓN NO SALARIAL | B9: 300000 | C9: 0 | D9: 300000 | E9: 600000 | F9: 450000
A10: 14200143 VACACIONES | B10: 418514 | C10: 120291 | D10: 1799623 | E10: 2338428 | F10: 130765
A11: 14200147 PRIMA DE SERVICIO | B11: 797976 | C11: 68611 | D11: 1944942 | E11: 2811529 | F11: 298753
A12: 14200148 CESANTIAS | B12: 801652 | C12: 107572 | D12: 1444942 | E12: 2354166 | F12: 298753
A13: 14200149 INTERESES DE CESANTIAS | B13: 90770 | C13: 0 | D13: 173400 | E13: 264170 | F13: 35853
A14: 14200156 APORTES SOBRE LA NÓMINA AL ICBF | B14: 254300 | C14: 0 | D14: 500200 | E14: 754500 | F14: 99800
... A21: TOTAL | B21: 14574690 | C21: 1119816 | D21: 28198718 | E21: 43893224 | F21: 5796152
A23: GASTOS OPERACIONALES
A24: 14400106 ARRENDAMIENTOS OFICINAS | B24: 2148748 | C24: 0 | D24: 14467814 | E24: 16616562 | F24: 0
A25: 14400108 SEGUROS (OFICINAS ACTIVOS ETC) | B25: 0 | C25: 0 | D25: 0 | E25: 0 | F25: 0
A26: 14400109 SERVICIOS SEGURIDAD Y VIGILANCIA | B26: 153564 | C26: 82557 | D26: 235100 | E26: 471221 | F26: 0
A27: 14400110 SERVICIO DE ACUEDUCTO ASEO Y ALCANTARILLADO | B27: 103630 | C27: 136830 | D27: 526587 | E27: 767047 | F27: 0
A28: 14400111 SERVICIO ENERGIA ELECTRICA | B28: 1743200 | C28: 398910 | D28: 1293273 | E28: 3435383 | F28: 0
A29: 14400112 SERVICIO DE TELEFONIA CELULARES | B29: 172207 | C29: 0 | D29: 2016807 | E29: 2189014 | F29: 0
A30: 14400113 SERVICIO DE INTERNET TELEFONO Y TELEVISION | B30: 1124760 | C30: 693397 | D30: 3487215 | E30: 5305372 | F30: 0
A31: 14400114 SERVICIO DE TRANSPORTE | B31: 200000 | C31: 0 | D31: 0 | E31: 200000 | F31: 0
A32: 14400115 SERVICIO DE GAS | B32: 3330 | C32: 19686 | D32: 13056 | E32: 36072 | F32: 0
A33: 14400116 GASTOS LEGALES MATRICULA MERCANTIL | B33: 5500 | C33: 0 | D33: 0 | E33: 5500 | F33: 0
A34: 14400117 GASTOS LEGALES GASTOS NOTARIALES | B34: 1726204 | C34: 0 | D34: 200559 | E34: 1926763 | F34: 0
A35: 14400118 GASTOS LEGALES TRAMITES Y PERMISOS | B35: 0 | C35: 0 | D35: 15400 | E35: 15400 | F35: 1000000
... A75: TOTAL | B75: 21370494 | C75: 5662444.4 | D75: 34117946 | E75: 61150884 | F75: 1552934.3
A77: TOTAL GASTO ADMINISTRATIVO | B77: 35945184
A79: GASTOS DE NOMINA
A80: 52050600 SUELDOS | B80: 15846542
A81: 52051500 HORAS EXTRAS Y RECARGOS | B81: 182290
A82: 52052700 AUXILIO DE TRANSPORTE | B82: 1305533
A83: 52053000 CESANTIAS | B83: 2130634.2
A84: 52053300 INTERESES SOBRE CESANTIAS | B84: 211672.88
A85: 52053600 PRIMA DE SERVICIOS | B85: 1826510.9
A86: 52053900 VACACIONES | B86: 3139762
A87: 52054501 AUXILIO DE VIVIENDA | B87: 1000000
A88: 52054502 AUXILIO DE ALIMENTACION | B88: 250000
A89: 52054801 BONIFICACIONES NO SALARIALES | B89: 250000
A90: 52056000 INDEMNIZACIONES LABORALES | B90: 976560
A91: 52056800 APORTES A ADMINISTRADORAS DE RIESGOS PRO | B91: 225200
... A102: TOTAL | B102: 37099005
A104: GASTOS OPERACIONALES
A105: 14400202 G.T.T. ASESORES | B105: 0 | C105: 0 | D105: 862500 | E105: 862500 | F105: 7230000
A106: 14400203 G.T.T. PROMOTORES | B106: 0 | C106: 0 | D106: 0 | E106: 0 | F106: 0
A107: 14400204 EVENTOS COMERCIALES | B107: 0 | C107: 0 | D107: 4149500 | E107: 4149500 | F107: 9782460
A108: 14400205 ALIMENTOS | B108: 0 | C108: 0 | D108: 199500 | E108: 199500
A109: 14400207 TELEFONIA CELULAR | B109: 0 | C109: 0 | D109: 0 | E109: 0 | F109: 0
A110: 14400208 PUBLICIDAD | B110: 0 | C110: 0 | D110: 1393389 | E110: 1393389 | F110: 0
A111: 14400209 CAPACITACION ASESORES COMERCIALES | B111: 0 | C111: 0 | D111: 0 | E111: 0 | F111: 0
A112: 14400210 ALIMENTACION PERSONAL EN EVENTO | B112: 0 | C112: 0 | D112: 397700 | E112: 397700 | F112: 938796
A113: 14400211 MANTENIMIENTOS ELEMENTOS COMERCIALES | B113: 0 | C113: 0 | D113: 82210 | E113: 82210 | F113: 0
A114: 14400212 OTROS GASTOS COMERCIALES | B114: 0 | C114: 0 | D114: 0 | E114: 0 | F114: 0
A115: 14400213 TRANSPORTES A EVENTOS | B115: 0 | C115: 0 | D115: 32700 | E115: 32700 | F115: 394000
A116: 14400214 BONIFICACION SPIFF | B116: 0 | C116: 0 | D116: 0 | E116: 0 | F116: 100000
A117: 14400215 PLATA EN MESA | B117: 0 | C117: 0 | D117: 0 | E117: 0 | F117: 0
A118: 14400216 QS POR AGENTE COMERCIAL | B118: 0 | C118: 0 | D118: 0 | E118: 0 | F118: 0
A119: 14400217 QS POR JEFE DE PROMOCIÓN | B119: 0 | C119: 0 | D119: 241000 | E119: 241000 | F119: 192000
A120: 14400218 BONIFICACIÓN E INCENTIVOS COMERCIALES | B120: 0 | C120: 0 | D120: 0 | E120: 0 | F120: 0
... A144: TOTAL | B144: 710642 | C144: 0 | D144: 12961102 | E144: 13671744 | F144: 20295706
A146: TOTAL GASTO COMERCIAL | B146: 37809647
A148: GASTOS DE NOMINA
A149: 51050600 SUELDOS | B149: 10133592
A150: 51052100 VIATICOS | B150: 1390000
A151: 51052400 INCAPACIDADES | B151: 137158
A152: 51052500 LICENCIA NO REMUNERADAS | B152: 0
A153: 51052700 AUXILIO DE TRANSPORTE | B153: 29404
A154: 51053000 CESANTIAS | B154: 862470
A155: 51053300 INTERESES SOBRE CESANTIAS | B155: 103498
A156: 51053600 PRIMA DE SERVICIOS | B156: 862470
A157: 51053900 VACACIONES | B157: 428418
A158: 51056800 APORTES ADMINISTRADORAS DE RIESGOS PROFE | B158: 124900
A159: 51056900 APORTES A ENTIDADES PROMOTORAS DE SALUD | B159: 869700
A160: 51057000 APORTES A FONDOS DE PENSION Y/O CESANTIA | B160: 1227800
... A164: TOTAL | B164: 17061610
A166: GASTOS OPERACIONALES
A167: 14400126 GASTOS DE VIAJE (VIATICOS) | B167: 0
A168: 14400127 GASTOS DE VIAJE (TIQUETES) | B168: 0
A169: 14400128 HOSPEDAJE HOTEL | B169: 0
A170: 51150500 INDUSTRIA Y COMERCIO | B170: 111956
A171: 51157001 IVA DESCONTABLE | B171: 1109478
A172: 51355000 TRANSPORTE FLETES Y ACARREOS | B172: 600000
A173: 51451000 CONSTRUCCIONES Y EDIFICACIONES | B173: 56302
A174: 51451500 MAQUINARIA Y EQUIPO | B174: 15000
A175: 51501000 ARREGLOS ORNAMENTALES | B175: 116000
A176: 51501500 REPARACIONES LOCATIVAS | B176: 34700
A177: 51550500 ALOJAMIENTO Y MANUTENCION | B177: 263282
A178: 52050600 SUELDOS | B178: 0
... A186: TOTAL | B186: 2706033
B188: SANDVILLE | F188: WESTVILLE
A189: 52051800 COMISIONES POR VENTAS | B189: 611047 | F189: 5260224
A190: 14400227 COMISIONES COMERCIALES POR VENTAS | B190: 6187270 | C190: 4482200 | D190: 43692386 | E190: 54361856 | F190: 23785424
A191: TOTAL COMISIONES | B191: 6798317 | C191: 4482200 | D191: 43692386 | E191: 54361856 | F191: 29045648
A193: COMISIONES DEL MES | B193: 0 | F193: 0
A194: COMSIONES SANDVILLE BEACH | B194: 0
A195: COMSIONES MES SANDVILLE DEL SOL | B195: -8814827
A196: COMSIONES MES SANDVILLE DEL MAR | B196: 15613144
B197: SANDVILLE | F197: WESTVILLE
...

Sheet SANDVILLE
A1: INFORME GENERAL DE GASTOS SANDVILLE SEPTIEMBRE 2018
A4: VENTAS | C4: RUBRO | D4: N° | E4: VALOR
C5: VENTAS DEL MES | D5: 5 | E5: 391200000
C6: a. VENTAS PROCESABLES | D6: 5 | E6: 391200000
C7: b. VENTAS NO PROCESABLES | D7: 0 | E7: 0
C8: VENTAS RADICADAS | D8: 5 | E8: 391200000
C9: VENTAS NO REGISTRABLES | D9: 0 | E9: 0
C10: RECAUDO POR VENTAS | D10: VALOR
C11: PLATA EN MESA | D11: 33893750
C12: PLATA EN MES | D12: 21000000
C13: TOTAL RECAUDO VENTAS DEL MES | D13: =+D11+D12 -> 54893750
C14: TOTAL RECAUDO CARTERA | D14: 328919119
C15: TOTAL INGRESO DEL MES | D15: =+D13+D14 -> 383812869
A16: CUENTA | D16: Mes Anterior | E16: Mes Actual | F16: Variacion | G16: %Ventas Brutas | H16: % Ventas Procesables | I16: %Recaudo Ventas Mes | J16: %Recaudo Cartera | K16: %Recaudo Total Mes
A17: COMERCIAL | B17: NOMINA COMERCIAL | C17: 52050600 SUELDOS | D17: 0 | E17: 6712850 | F17: =IFERROR(+(E17-D17)/D17,"N/A") -> N/A | G17: =+E17/$E$5 -> 0.017159637 | H17: =+E17/$E$6 -> 0.017159637 | I17: =+E17/$D$13 -> 0.12228806 | J17: =+E17/$D$14 -> 0.020408817 | K17: =+E17/$D$15 -> 0.017489903
C18: 52051500 HORAS EXTRAS Y RECARGOS | D18: 0 | E18: 113931 | F18: =IFERROR(+(E18-D18)/D18,"N/A") -> N/A | G18: =+E18/$E$5 -> 0.00029123466 | H18: =+E18/$E$6 -> 0.00029123466 | I18: =+E18/$D$13 -> 0.0020754822 | J18: =+E18/$D$14 -> 0.00034637999 | K18: =+E18/$D$15 -> 0.00029683997
C19: 52052700 AUXILIO DE TRANSPORTE | D19: 0 | E19: 598369.5 | F19: =IFERROR(+(E19-D19)/D19,"N/A") -> N/A | G19: =+E19/$E$5 -> 0.0015295744 | H19: =+E19/$E$6 -> 0.0015295744 | I19: =+E19/$D$13 -> 0.010900503 | J19: =+E19/$D$14 -> 0.0018191995 | K19: =+E19/$D$15 -> 0.0015590136
C20: 52053000 CESANTIAS | D20: 0 | E20: 1452011.5 | F20: =IFERROR(+(E20-D20)/D20,"N/A") -> N/A | G20: =+E20/$E$5 -> 0.0037116858 | H20: =+E20/$E$6 -> 0.0037116858 | I20: =+E20/$D$13 -> 0.026451308 | J20: =+E20/$D$14 -> 0.0044144941 | K20: =+E20/$D$15 -> 0.0037831235
C21: 52053300 INTERESES SOBRE CESANTIAS | D21: 0 | E21: 69255 | F21: =IFERROR(+(E21-D21)/D21,"N/A") -> N/A | G21: =+E21/$E$5 -> 0.00017703221 | H21: =+E21/$E$6 -> 0.00017703221 | I21: =+E21/$D$13 -> 0.001261619 | J21: =+E21/$D$14 -> 0.00021055328 | K21: =+E21/$D$15 -> 0.00018043949
C22: 52053600 PRIMA DE SERVICIOS | D22: 0 | E22: 895921.5 | F22: =IFERROR(+(E22-D22)/D22,"N/A") -> N/A | G22: =+E22/$E$5 -> 0.0022901879 | H22: =+E22/$E$6 -> 0.0022901879 | I22: =+E22/$D$13 -> 0.016321011 | J22: =+E22/$D$14 -> 0.0027238353 | K22: =+E22/$D$15 -> 0.0023342664
C23: 52053900 VACACIONES | D23: 0 | E23: 1039323 | F23: =IFERROR(+(E23-D23)/D23,"N/A") -> N/A | G23: =+E23/$E$5 -> 0.0026567561 | H23: =+E23/$E$6 -> 0.0026567561 | I23: =+E23/$D$13 -> 0.018933358 | J23: =+E23/$D$14 -> 0.0031598133 | K23: =+E23/$D$15 -> 0.0027078899
C24: 52054501 AUXILIO DE VIVIENDA | D24: 0 | E24: 250000 | F24: =IFERROR(+(E24-D24)/D24,"N/A") -> N/A | G24: =+E24/$E$5 -> 0.0006390593 | H24: =+E24/$E$6 -> 0.0006390593 | I24: =+E24/$D$13 -> 0.0045542525 | J24: =+E24/$D$14 -> 0.00076006527 | K24: =+E24/$D$15 -> 0.00065135909
C25: 52054502 AUXILIO DE ALIMENTACION | D25: 0 | E25: 250000 | F25: =IFERROR(+(E25-D25)/D25,"N/A") -> N/A | G25: =+E25/$E$5 -> 0.0006390593 | H25: =+E25/$E$6 -> 0.0006390593 | I25: =+E25/$D$13 -> 0.0045542525 | J25: =+E25/$D$14 -> 0.00076006527 | K25: =+E25/$D$15 -> 0.00065135909
C26: 52056800 APORTES A ADMINISTRADORAS DE RIESGOS PRO | D26: 0 | E26: 121150 | F26: =IFERROR(+(E26-D26)/D26,"N/A") -> N/A | G26: =+E26/$E$5 -> 0.00030968814 | H26: =+E26/$E$6 -> 0.00030968814 | I26: =+E26/$D$13 -> 0.0022069908 | J26: =+E26/$D$14 -> 0.00036832763 | K26: =+E26/$D$15 -> 0.00031564861
C27: 52056900 APORTES A ENTIDADES PROMOTORAS DE SALUD | D27: 0 | E27: 1262250 | F27: =IFERROR(+(E27-D27)/D27,"N/A") -> N/A | G27: =+E27/$E$5 -> 0.0032266104 | H27: =+E27/$E$6 -> 0.0032266104 | I27: =+E27/$D$13 -> 0.022994421 | J27: =+E27/$D$14 -> 0.0038375696 | K27: =+E27/$D$15 -> 0.003288712
C28: 52057000 APORTES A FONDOS DE PENSION Y/O CESANTIA | D28: 0 | E28: 2786050 | F28: =IFERROR(+(E28-D28)/D28,"N/A") -> N/A | G28: =+E28/$E$5 -> 0.0071218047 | H28: =+E28/$E$6 -> 0.0071218047 | I28: =+E28/$D$13 -> 0.050753501 | J28: =+E28/$D$14 -> 0.0084703194 | K28: =+E28/$D$15 -> 0.0072588759
C29: 52057200 APORTES CAJAS DE COMPENSACION FAMILIAR | D29: 0 | E29: 725550 | F29: =IFERROR(+(E29-D29)/D29,"N/A") -> N/A | G29: =+E29/$E$5 -> 0.0018546779 | H29: =+E29/$E$6 -> 0.0018546779 | I29: =+E29/$D$13 -> 0.013217352 | J29: =+E29/$D$14 -> 0.0022058614 | K29: =+E29/$D$15 -> 0.0018903743
... C35: TOTAL NOMINA COMERCIAL | D35: 0 | E35: 16784326 | F35: =IFERROR(+(E35-D35)/D35,"N/A") -> N/A | G35: =+E35/$E$5 -> 0.04290472 | H35: =+E35/$E$6 -> 0.04290472 | I35: =+E35/$D$13 -> 0.30576025 | J35: =+E35/$D$14 -> 0.051028735 | K35: =+E35/$D$15 -> 0.043730494
B36: OPERACIÓN COMERCIAL | C36: 14400202 G.T.T. ASESORES | D36: 862500 | E36: 5275000 | F36: =IFERROR(+(E36-D36)/D36,"N/A") -> 5.115942 | G36: =+E36/$E$5 -> 0.013484151 | H36: =+E36/$E$6 -> 0.013484151 | I36: =+E36/$D$13 -> 0.096094728 | J36: =+E36/$D$14 -> 0.016037377 | K36: =+E36/$D$15 -> 0.013743677
C37: 14400203 G.T.T. PROMOTORES | D37: 0 | E37: 75000 | F37: =IFERROR(+(E37-D37)/D37,"N/A") -> N/A | G37: =+E37/$E$5 -> 0.00019171779 | H37: =+E37/$E$6 -> 0.00019171779 | I37: =+E37/$D$13 -> 0.0013662758 | J37: =+E37/$D$14 -> 0.00022801958 | K37: =+E37/$D$15 -> 0.00019540773
C38: 14400204 EVENTOS COMERCIALES | D38: 4149500 | E38: 175050 | F38: =IFERROR(+(E38-D38)/D38,"N/A") -> -0.95781419 | G38: =+E38/$E$5 -> 0.00044746933 | H38: =+E38/$E$6 -> 0.00044746933 | I38: =+E38/$D$13 -> 0.0031888876 | J38: =+E38/$D$14 -> 0.0005321977 | K38: =+E38/$D$15 -> 0.00045608163
C39: 14400205 ALIMENTOS | D39: 199500 | E39: 371796 | F39: =IFERROR(+(E39-D39)/D39,"N/A") -> 0.8636391 | G39: =+E39/$E$5 -> 0.00095039877 | H39: =+E39/$E$6 -> 0.00095039877 | I39: =+E39/$D$13 -> 0.0067730115 | J39: =+E39/$D$14 -> 0.0011303569 | K39: =+E39/$D$15 -> 0.00096869081
C40: 14400210 ALIMENTACION PERSONAL EN EVENTO | D40: 397700 | E40: 447698 | F40: =IFERROR(+(E40-D40)/D40,"N/A") -> 0.12571788 | G40: =+E40/$E$5 -> 0.0011444223 | H40: =+E40/$E$6 -> 0.0011444223 | I40: =+E40/$D$13 -> 0.008155719 | J40: =+E40/$D$14 -> 0.0013611188 | K40: =+E40/$D$15 -> 0.0011664486
C41: 14400212 OTROS GASTOS COMERCIALES | D41: 0 | E41: 25650 | F41: =IFERROR(+(E41-D41)/D41,"N/A") -> N/A | G41: =+E41/$E$5 -> 6.5567485e-05 | H41: =+E41/$E$6 -> 6.5567485e-05 | I41: =+E41/$D$13 -> 0.00046726631 | J41: =+E41/$D$14 -> 7.7982697e-05 | K41: =+E41/$D$15 -> 6.6829442e-05
C42: 14400213 TRANSPORTES A EVENTOS | D42: 32700 | E42: 140000 | F42: =IFERROR(+(E42-D42)/D42,"N/A") -> 3.2813456 | G42: =+E42/$E$5 -> 0.00035787321 | H42: =+E42/$E$6 -> 0.00035787321 | I42: =+E42/$D$13 -> 0.0025503814 | J42: =+E42/$D$14 -> 0.00042563655 | K42: =+E42/$D$15 -> 0.00036476109
C43: 14400214 BONIFICACION SPIFF | D43: 0 | E43: 250000 | F43: =IFERROR(+(E43-D43)/D43,"N/A") -> N/A | G43: =+E43/$E$5 -> 0.0006390593 | H43: =+E43/$E$6 -> 0.0006390593 | I43: =+E43/$D$13 -> 0.0045542525 | J43: =+E43/$D$14 -> 0.00076006527 | K43: =+E43/$D$15 -> 0.00065135909
C44: 14400215 PLATA EN MESA | D44: 0 | E44: 100000 | F44: =IFERROR(+(E44-D44)/D44,"N/A") -> N/A | G44: =+E44/$E$5 -> 0.00025562372 | H44: =+E44/$E$6 -> 0.00025562372 | I44: =+E44/$D$13 -> 0.001821701 | J44: =+E44/$D$14 -> 0.00030402611 | K44: =+E44/$D$15 -> 0.00026054363
C45: 14400217 QS POR JEFE DE PROMOCIÓN | D45: 241000 | E45: 104500 | F45: =IFERROR(+(E45-D45)/D45,"N/A") -> -0.56639004 | G45: =+E45/$E$5 -> 0.00026712679 | H45: =+E45/$E$6 -> 0.00026712679 | I45: =+E45/$D$13 -> 0.0019036776 | J45: =+E45/$D$14 -> 0.00031770728 | K45: =+E45/$D$15 -> 0.0002722681
C46: 14400219 HOSSTES | D46: 285000 | E46: 280000 | F46: =IFERROR(+(E46-D46)/D46,"N/A") -> -0.01754386 | G46: =+E46/$E$5 -> 0.00071574642 | H46: =+E46/$E$6 -> 0.00071574642 | I46: =+E46/$D$13 -> 0.0051007628 | J46: =+E46/$D$14 -> 0.00085127311 | K46: =+E46/$D$15 -> 0.00072952218
C47: 14400221 GASTOS POR ÚTILES Y PAPELERÍA | D47: 155681 | E47: 67815 | F47: =IFERROR(+(E47-D47)/D47,"N/A") -> -0.56439771 | G47: =+E47/$E$5 -> 0.00017335123 | H47: =+E47/$E$6 -> 0.00017335123 | I47: =+E47/$D$13 -> 0.0012353865 | J47: =+E47/$D$14 -> 0.00020617531 | K47: =+E47/$D$15 -> 0.00017668767
C48: 14400222 PAPELERIA PARA PROMOCION/VENTAS | D48: 24000 | E48: 25000 | F48: =IFERROR(+(E48-D48)/D48,"N/A") -> 0.041666667 | G48: =+E48/$E$5 -> 6.390593e-05 | H48: =+E48/$E$6 -> 6.390593e-05 | I48: =+E48/$D$13 -> 0.00045542525 | J48: =+E48/$D$14 -> 7.6006527e-05 | K48: =+E48/$D$15 -> 6.5135909e-05
... C56: 14400248 ARRENDAMIENTOS DE BIENES INMUEBLES | D56: 2480000 | E56: 0 | F56: =IFERROR(+(E56-D56)/D56,"N/A") -> -1 | G56: =+E56/$E$5 -> 0 | H56: =+E56/$E$6 -> 0 | I56: =+E56/$D$13 -> 0 | J56: =+E56/$D$14 -> 0 | K56: =+E56/$D$15 -> 0
C57: TOTAL OPERACION COMERCIAL | D57: 12196145 | E57: =SUM(E36:E56) -> 11695770 | F57: =IFERROR(+(E57-D57)/D57,"N/A") -> -0.041027308 | G57: =+E57/$E$5 -> 0.029897163 | H57: =+E57/$E$6 -> 0.029897163 | I57: =+E57/$D$13 -> 0.21306196 | J57: =+E57/$D$14 -> 0.035558194 | K57: =+E57/$D$15 -> 0.030472584
B58: TOTAL OPERACIÓN COMERCIAL ANTES DE COMISIONES | D58: 12196145 | E58: =+E35+E57 -> 28480096 | F58: =+(E58-D58)/D58 -> 1.335172 | G58: =+E58/$E$5 -> 0.072801883 | H58: =+E58/$E$6 -> 0.072801883 | I58: =+E58/$D$13 -> 0.51882221 | J58: =+E58/$D$14 -> 0.086586929 | K58: =+E58/$D$15 -> 0.074203079
B59: COMIS | C59: 14400227 COMISIONES COMERCIALES POR VENTAS DEL MES | D59: 0 | E59: 1961787 | F59: =IFERROR(+(E59-D59)/D59,"N/A") -> N/A | G59: =+E59/$E$5 -> 0.0050147929 | H59: =+E59/$E$6 -> 0.0050147929 | I59: =+E59/$D$13 -> 0.035737894 | J59: =+E59/$D$14 -> 0.0059643447 | K59: =+E59/$D$15 -> 0.0051113112
C60: 14400227 COMISIONES COMERCIALES POR VENTAS DE OTROS MESES | D60: 54361856 | E60: 38797886 | F60: =IFERROR(+(E60-D60)/D60,"N/A") -> -0.28630314 | G60: =+E60/$E$5 -> 0.0991766 | H60: =+E60/$E$6 -> 0.0991766 | I60: =+E60/$D$13 -> 0.70678148 | J60: =+E60/$D$14 -> 0.1179557 | K60: =+E60/$D$15 -> 0.10108542
C61: TOTAL COMISIONES POR VENTAS | D61: 54361856 | E61: =SUM(E59:E60) -> 40759673 | F61: =IFERROR(+(E61-D61)/D61,"N/A") -> -0.25021557 | G61: =+E61/$E$5 -> 0.10419139 | H61: =+E61/$E$6 -> 0.10419139 | I61: =+E61/$D$13 -> 0.74251938 | J61: =+E61/$D$14 -> 0.12392005 | K61: =+E61/$D$15 -> 0.10619673
A62: ADMINISRTRACION | B62: NOMINA ADMINISTRACION | C62: 14200101 SUELDOS Y SALARIOS | D62: 26601395 | E62: 22254254 | F62: =IFERROR(+(E62-D62)/D62,"N/A") -> -0.16341778 | G62: =+E62/$E$5 -> 0.056887152 | H62: =+E62/$E$6 -> 0.056887152 | I62: =+E62/$D$13 -> 0.40540597 | J62: =+E62/$D$14 -> 0.067658743 | K62: =+E62/$D$15 -> 0.057982042
C63: 14200107 SUBSIDIO DE TRANSPORTE | D63: 1443736 | E63: 1037960 | F63: =IFERROR(+(E63-D63)/D63,"N/A") -> -0.2810597 | G63: =+E63/$E$5 -> 0.002653272 | H63: =+E63/$E$6 -> 0.002653272 | I63: =+E63/$D$13 -> 0.018908528 | J63: =+E63/$D$14 -> 0.0031556694 | K63: =+E63/$D$15 -> 0.0027043387
C64: 14200116 BONIFICACIÓN NO SALARIAL | D64: 600000 | E64: 600000 | F64: =IFERROR(+(E64-D64)/D64,"N/A") -> 0 | G64: =+E64/$E$5 -> 0.0015337423 | H64: =+E64/$E$6 -> 0.0015337423 | I64: =+E64/$D$13 -> 0.010930206 | J64: =+E64/$D$14 -> 0.0018241567 | K64: =+E64/$D$15 -> 0.0015632618
C65: 14200143 VACACIONES | D65: 2338428 | E65: 940230 | F65: =IFERROR(+(E65-D65)/D65,"N/A") -> -0.59792219 | G65: =+E65/$E$5 -> 0.0024034509 | H65: =+E65/$E$6 -> 0.0024034509 | I65: =+E65/$D$13 -> 0.017128179 | J65: =+E65/$D$14 -> 0.0028585447 | K65: =+E65/$D$15 -> 0.0024497094
C66: 14200147 PRIMA DE SERVICIO | D66: 2811529 | E66: 1966960 | F66: =IFERROR(+(E66-D66)/D66,"N/A") -> -0.30039491 | G66: =+E66/$E$5 -> 0.0050280164 | H66: =+E66/$E$6 -> 0.0050280164 | I66: =+E66/$D$13 -> 0.03583213 | J66: =+E66/$D$14 -> 0.005980072 | K66: =+E66/$D$15 -> 0.0051247891
C67: 14200148 CESANTIAS | D67: 2354166 | E67: 1966960 | F67: =IFERROR(+(E67-D67)/D67,"N/A") -> -0.16447693 | G67: =+E67/$E$5 -> 0.0050280164 | H67: =+E67/$E$6 -> 0.0050280164 | I67: =+E67/$D$13 -> 0.03583213 | J67: =+E67/$D$14 -> 0.005980072 | K67: =+E67/$D$15 -> 0.0051247891
C68: 14200149 INTERESES DE CESANTIAS | D68: 264170 | E68: 236045 | F68: =IFERROR(+(E68-D68)/D68,"N/A") -> -0.10646553 | G68: =+E68/$E$5 -> 0.00060338701 | H68: =+E68/$E$6 -> 0.00060338701 | I68: =+E68/$D$13 -> 0.0043000342 | J68: =+E68/$D$14 -> 0.00071763843 | K68: =+E68/$D$15 -> 0.00061500022
C69: 14200156 APORTES SOBRE LA NÓMINA AL ICBF | D69: 754500 | E69: 674200 | F69: =IFERROR(+(E69-D69)/D69,"N/A") -> -0.1064281 | G69: =+E69/$E$5 -> 0.0017234151 | H69: =+E69/$E$6 -> 0.0017234151 | I69: =+E69/$D$13 -> 0.012281908 | J69: =+E69/$D$14 -> 0.002049744 | K69: =+E69/$D$15 -> 0.0017565852
C70: 14200157 APORTES SOBRE LA NÓMINA AL SENA | D70: 503400 | E70: 449700 | F70: =IFERROR(+(E70-D70)/D70,"N/A") -> -0.10667461 | G70: =+E70/$E$5 -> 0.0011495399 | H70: =+E70/$E$6 -> 0.0011495399 | I70: =+E70/$D$13 -> 0.0081921895 | J70: =+E70/$D$14 -> 0.0013672054 | K70: =+E70/$D$15 -> 0.0011716647
C71: 14200158 APORTES SOBRE LA NÓMINA ARL | D71: 182300 | E71: 166900 | F71: =IFERROR(+(E71-D71)/D71,"N/A") -> -0.084476138 | G71: =+E71/$E$5 -> 0.00042663599 | H71: =+E71/$E$6 -> 0.00042663599 | I71: =+E71/$D$13 -> 0.003040419 | J71: =+E71/$D$14 -> 0.00050741958 | K71: =+E71/$D$15 -> 0.00043484733
C72: 14200159 APORTES SOBRE LA NÓMINA SALUD-EPS | D72: 2134200 | E72: 1917200 | F72: =IFERROR(+(E72-D72)/D72,"N/A") -> -0.10167744 | G72: =+E72/$E$5 -> 0.004900818 | H72: =+E72/$E$6 -> 0.004900818 | I72: =+E72/$D$13 -> 0.034925652 | J72: =+E72/$D$14 -> 0.0058287886 | K72: =+E72/$D$15 -> 0.0049951426
C73: 14200160 APORTES SOBRE LA NÓMINA PENSIONES Y/O CESANTÍAS | D73: 2899800 | E73: 2707100 | F73: =IFERROR(+(E73-D73)/D73,"N/A") -> -0.066452859 | G73: =+E73/$E$5 -> 0.0069199898 | H73: =+E73/$E$6 -> 0.0069199898 | I73: =+E73/$D$13 -> 0.049315268 | J73: =+E73/$D$14 -> 0.0082302908 | K73: =+E73/$D$15 -> 0.0070531767
C74: 14200161 APORTES SOBRE LA NÓMINA APORTES CAJAS DE COMPENSAC | D74: 1005600 | E74: 895100 | F74: =IFERROR(+(E74-D74)/D74,"N/A") -> -0.10988465 | G74: =+E74/$E$5 -> 0.0022880879 | H74: =+E74/$E$6 -> 0.0022880879 | I74: =+E74/$D$13 -> 0.016306046 | J74: =+E74/$D$14 -> 0.0027213377 | K74: =+E74/$D$15 -> 0.0023321261
C75: 14400163 PRESTACIÓN DE SERVICIO | D75: 3000000 | E75: 3000000 | F75: =IFERROR(+(E75-D75)/D75,"N/A") -> 0 | G75: =+E75/$E$5 -> 0.0076687117 | H75: =+E75/$E$6 -> 0.0076687117 | I75: =+E75/$D$13 -> 0.05465103 | J75: =+E75/$D$14 -> 0.0091207833 | K75: =+E75/$D$15 -> 0.007816309
C76: TOTAL NOMINA ADMINISTRACION | D76: 46893224 | E76: =SUM(E62:E75) -> 38812609 | F76: =IFERROR(+(E76-D76)/D76,"N/A") -> -0.17231946 | G76: =+E76/$E$5 -> 0.099214236 | H76: =+E76/$E$6 -> 0.099214236 | I76: =+E76/$D$13 -> 0.70704969 | J76: =+E76/$D$14 -> 0.11800047 | K76: =+E76/$D$15 -> 0.10112378
B77: OPERACIÓN ADMINISTRACION | C77: 14400106 ARRENDAMIENTOS OFICINAS | D77: 16616562 | E77: 14510051 | F77: =IFERROR(+(E77-D77)/D77,"N/A") -> -0.12677177 | G77: =+E77/$E$5 -> 0.037091132 | H77: =+E77/$E$6 -> 0.037091132 | I77: =+E77/$D$13 -> 0.26432975 | J77: =+E77/$D$14 -> 0.044114344 | K77: =+E77/$D$15 -> 0.037805014
C78: 14400109 SERVICIOS SEGURIDAD Y VIGILANCIA | D78: 471221 | E78: 898404 | F78: =IFERROR(+(E78-D78)/D78,"N/A") -> 0.90654491 | G78: =+E78/$E$5 -> 0.0022965337 | H78: =+E78/$E$6 -> 0.0022965337 | I78: =+E78/$D$13 -> 0.016366235 | J78: =+E78/$D$14 -> 0.0027313827 | K78: =+E78/$D$15 -> 0.0023407344
C79: 14400110 SERVICIO DE ACUEDUCTO ASEO Y ALCANTARILLADO | D79: 767047 | E79: 770986 | F79: =IFERROR(+(E79-D79)/D79,"N/A") -> 0.0051352785 | G79: =+E79/$E$5 -> 0.0019708231 | H79: =+E79/$E$6 -> 0.0019708231 | I79: =+E79/$D$13 -> 0.01404506 | J79: =+E79/$D$14 -> 0.0023439987 | K79: =+E79/$D$15 -> 0.0020087549
C80: 14400111 SERVICIO ENERGIA ELECTRICA | D80: 3435383 | E80: 3134509 | F80: =IFERROR(+(E80-D80)/D80,"N/A") -> -0.087580919 | G80: =+E80/$E$5 -> 0.0080125486 | H80: =+E80/$E$6 -> 0.0080125486 | I80: =+E80/$D$13 -> 0.057101382 | J80: =+E80/$D$14 -> 0.0095297258 | K80: =+E80/$D$15 -> 0.0081667637
C81: 14400112 SERVICIO DE TELEFONIA CELULARES | D81: 2189014 | E81: 2356346 | F81: =IFERROR(+(E81-D81)/D81,"N/A") -> 0.076441722 | G81: =+E81/$E$5 -> 0.0060233793 | H81: =+E81/$E$6 -> 0.0060233793 | I81: =+E81/$D$13 -> 0.042925579 | J81: =+E81/$D$14 -> 0.0071639071 | K81: =+E81/$D$15 -> 0.0061393095
C82: 14400113 SERVICIO DE INTERNET TELEFONO Y TELEVISION | D82: 5305372 | E82: 4381866 | F82: =IFERROR(+(E82-D82)/D82,"N/A") -> -0.17406998 | G82: =+E82/$E$5 -> 0.011201089 | H82: =+E82/$E$6 -> 0.011201089 | I82: =+E82/$D$13 -> 0.079824497 | J82: =+E82/$D$14 -> 0.013322017 | K82: =+E82/$D$15 -> 0.011416673
C83: 14400114 SERVICIO DE TRANSPORTE | D83: 200000 | E83: 400000 | F83: =IFERROR(+(E83-D83)/D83,"N/A") -> 1 | G83: =+E83/$E$5 -> 0.0010224949 | H83: =+E83/$E$6 -> 0.0010224949 | I83: =+E83/$D$13 -> 0.0072868041 | J83: =+E83/$D$14 -> 0.0012161044 | K83: =+E83/$D$15 -> 0.0010421745
C84: 14400115 SERVICIO DE GAS | D84: 36072 | E84: 31580 | F84: =IFERROR(+(E84-D84)/D84,"N/A") -> -0.12452872 | G84: =+E84/$E$5 -> 8.0725971e-05 | H84: =+E84/$E$6 -> 8.0725971e-05 | I84: =+E84/$D$13 -> 0.00057529318 | J84: =+E84/$D$14 -> 9.6011445e-05 | K84: =+E84/$D$15 -> 8.227968e-05
C85: 14400117 GASTOS LEGALES GASTOS NOTARIALES | D85: 1926763 | E85: 341748 | F85: =IFERROR(+(E85-D85)/D85,"N/A") -> -0.82263101 | G85: =+E85/$E$5 -> 0.00087358896 | H85: =+E85/$E$6 -> 0.00087358896 | I85: =+E85/$D$13 -> 0.0062256268 | J85: =+E85/$D$14 -> 0.0010390031 | K85: =+E85/$D$15 -> 0.00089040266
C86: 14400118 GASTOS LEGALES TRAMITES Y PERMISOS | D86: 15400 | E86: 292180 | F86: =IFERROR(+(E86-D86)/D86,"N/A") -> 17.972727 | G86: =+E86/$E$5 -> 0.00074688139 | H86: =+E86/$E$6 -> 0.00074688139 | I86: =+E86/$D$13 -> 0.005322646 | J86: =+E86/$D$14 -> 0.00088830349 | K86: =+E86/$D$15 -> 0.00076125639
C87: 14400119 GASTOS PROCESOS LEGALES EN CONTRA | D87: 0 | E87: 600000 | F87: =IFERROR(+(E87-D87)/D87,"N/A") -> N/A | G87: =+E87/$E$5 -> 0.0015337423 | H87: =+E87/$E$6 -> 0.0015337423 | I87: =+E87/$D$13 -> 0.010930206 | J87: =+E87/$D$14 -> 0.0018241567 | K87: =+E87/$D$15 -> 0.0015632618
C88: 14400120 MANTENIMIENTO Y REPARACIONES | D88: 1323777 | E88: 256000 | F88: =IFERROR(+(E88-D88)/D88,"N/A") -> -0.80661395 | G88: =+E88/$E$5 -> 0.00065439673 | H88: =+E88/$E$6 -> 0.00065439673 | I88: =+E88/$D$13 -> 0.0046635546 | J88: =+E88/$D$14 -> 0.00077830684 | K88: =+E88/$D$15 -> 0.00066699171
C89: 14400122 MANTENIMIENTO DE REDES Y EQUIPO DE COMPUTO | D89: 230000 | E89: 258276 | F89: =IFERROR(+(E89-D89)/D89,"N/A") -> 0.12293913 | G89: =+E89/$E$5 -> 0.00066021472 | H89: =+E89/$E$6 -> 0.00066021472 | I89: =+E89/$D$13 -> 0.0047050165 | J89: =+E89/$D$14 -> 0.00078522647 | K89: =+E89/$D$15 -> 0.00067292168
C90: 14400124 GASTOS DE CONDOMINIO ( SOSTENIMIENTO DEL PROYECTO) | D90: 765974 | E90: =5255000-4760000 -> 495000 | F90: =IFERROR(+(E90-D90)/D90,"N/A") -> -0.35376397 | G90: =+E90/$E$5 -> 0.0012653374 | H90: =+E90/$E$6 -> 0.0012653374 | I90: =+E90/$D$13 -> 0.00901742 | J90: =+E90/$D$14 -> 0.0015049292 | K90: =+E90/$D$15 -> 0.001289691
C91: 14400125 ADECUACIÓN E INSTALACIÓN DE OFICINAS | D91: 2705904 | E91: 1200000 | F91: =IFERROR(+(E91-D91)/D91,"N/A") -> -0.55652529 | G91: =+E91/$E$5 -> 0.0030674847 | H91: =+E91/$E$6 -> 0.0030674847 | I91: =+E91/$D$13 -> 0.021860412 | J91: =+E91/$D$14 -> 0.0036483133 | K91: =+E91/$D$15 -> 0.0031265236
C92: 14400126 GASTOS DE VIAJE (VIATICOS) | D92: 1006000 | E92: 830100 | F92: =IFERROR(+(E92-D92)/D92,"N/A") -> -0.17485089 | G92: =+E92/$E$5 -> 0.0021219325 | H92: =+E92/$E$6 -> 0.0021219325 | I92: =+E92/$D$13 -> 0.01512194 | J92: =+E92/$D$14 -> 0.0025237207 | K92: =+E92/$D$15 -> 0.0021627727
C93: 14400127 GASTOS DE VIAJE (TIQUETES) | D93: 976290 | E93: 360290 | F93: =IFERROR(+(E93-D93)/D93,"N/A") -> -0.63096006 | G93: =+E93/$E$5 -> 0.00092098671 | H93: =+E93/$E$6 -> 0.00092098671 | I93: =+E93/$D$13 -> 0.0065634066 | J93: =+E93/$D$14 -> 0.0010953757 | K93: =+E93/$D$15 -> 0.00093871266
C94: 14400128 HOSPEDAJE HOTEL | D94: 0 | E94: 1754163 | F94: =IFERROR(+(E94-D94)/D94,"N/A") -> N/A | G94: =+E94/$E$5 -> 0.0044840567 | H94: =+E94/$E$6 -> 0.0044840567 | I94: =+E94/$D$13 -> 0.031955605 | J94: =+E94/$D$14 -> 0.0053331135 | K94: =+E94/$D$15 -> 0.00457036
C95: 14400131 DIVERSOS ASEO Y CAFETERIA | D95: 2387672 | E95: 2567850 | F95: =IFERROR(+(E95-D95)/D95,"N/A") -> 0.075461789 | G95: =+E95/$E$5 -> 0.0065640337 | H95: =+E95/$E$6 -> 0.0065640337 | I95: =+E95/$D$13 -> 0.046778549 | J95: =+E95/$D$14 -> 0.0078069344 | K95: =+E95/$D$15 -> 0.0066903697
C96: 14400132 DIVERSOS MENSAJERIA-TRANSPORTE | D96: 2356400 | E96: 1614633 | F96: =IFERROR(+(E96-D96)/D96,"N/A") -> -0.31478824 | G96: =+E96/$E$5 -> 0.004127385 | H96: =+E96/$E$6 -> 0.004127385 | I96: =+E96/$D$13 -> 0.029413786 | J96: =+E96/$D$14 -> 0.0049089059 | K96: =+E96/$D$15 -> 0.0042068235
C97: 14400133 DIVERSOS UTILES DE OFICINA | D97: 835244 | E97: 1293177 | F97: =IFERROR(+(E97-D97)/D97,"N/A") -> 0.54826254 | G97: =+E97/$E$5 -> 0.0033056672 | H97: =+E97/$E$6 -> 0.0033056672 | I97: =+E97/$D$13 -> 0.023557819 | J97: =+E97/$D$14 -> 0.0039315957 | K97: =+E97/$D$15 -> 0.0033692904
C98: 14400134 DIVERSOS FIESTAS EMPRESARIALES | D98: 0 | E98: 79000 | F98: =IFERROR(+(E98-D98)/D98,"N/A") -> N/A | G98: =+E98/$E$5 -> 0.00020194274 | H98: =+E98/$E$6 -> 0.00020194274 | I98: =+E98/$D$13 -> 0.0014391438 | J98: =+E98/$D$14 -> 0.00024018063 | K98: =+E98/$D$15 -> 0.00020582947
C99: 14400142 IMPUESTOS IVA DESCONTABLE | D99: 0 | E99: 32574 | F99: =IFERROR(+(E99-D99)/D99,"N/A") -> N/A | G99: =+E99/$E$5 -> 8.3266871e-05 | H99: =+E99/$E$6 -> 8.3266871e-05 | I99: =+E99/$D$13 -> 0.00059340089 | J99: =+E99/$D$14 -> 9.9033465e-05 | K99: =+E99/$D$15 -> 8.4869484e-05
C100: 14400143 OTROS IMPUESTOS | D100: 294872 | E100: 10422 | F100: =IFERROR(+(E100-D100)/D100,"N/A") -> -0.96465585 | G100: =+E100/$E$5 -> 2.6641104e-05 | H100: =+E100/$E$6 -> 2.6641104e-05 | I100: =+E100/$D$13 -> 0.00018985768 | J100: =+E100/$D$14 -> 3.1685601e-05 | K100: =+E100/$D$15 -> 2.7153858e-05
C101: 14400144 GASTOS BANCARIOS COMISIONES | D101: 5032103.6 | E101: 4652190 | F101: =IFERROR(+(E101-D101)/D101,"N/A") -> -0.075497971 | G101: =+E101/$E$5 -> 0.011892101 | H101: =+E101/$E$6 -> 0.011892101 | I101: =+E101/$D$13 -> 0.084748992 | J101: =+E101/$D$14 -> 0.014143872 | K101: =+E101/$D$15 -> 0.012120985
C102: 14400145 GASTOS BANCARIOS INTERESES | D102: 35484.95 | E102: -17 | F102: =IFERROR(+(E102-D102)/D102,"N/A") -> -1.0004791 | G102: =+E102/$E$5 -> -4.3456033e-08 | H102: =+E102/$E$6 -> -4.3456033e-08 | I102: =+E102/$D$13 -> -3.0968917e-07 | J102: =+E102/$D$14 -> -5.1684439e-08 | K102: =+E102/$D$15 -> -4.4292418e-08
... C117: 14400179 SERVICIO DE PARQUEADERO | D117: 0 | E117: 267227 | F117: =IFERROR(+(E117-D117)/D117,"N/A") -> N/A | G117: =+E117/$E$5 -> 0.0006830956 | H117: =+E117/$E$6 -> 0.0006830956 | I117: =+E117/$D$13 -> 0.004868077 | J117: =+E117/$D$14 -> 0.00081243985 | K117: =+E117/$D$15 -> 0.00069624294
C118: TOTAL GASTO ADMINISTRACION | D118: 61144665 | E118: =SUM(E77:E117) -> 56020515 | F118: =IFERROR(+(E118-D118)/D118,"N/A") -> -0.083803711 | G118: =+E118/$E$5 -> 0.14320173 | H118: =+E118/$E$6 -> 0.14320173 | I118: =+E118/$D$13 -> 1.0205263 | J118: =+E118/$D$14 -> 0.17031699 | K118: =+E118/$D$15 -> 0.14595789
B119: TOTAL OPERACIÓN ADMINISTRACION | D119: 1.0803789e+08 | E119: =+E118+E76 -> 94833124 | F119: =IFERROR(+(E119-D119)/D119,"N/A") -> -0.12222346 | G119: =+E119/$E$5 -> 0.24241596 | H119: =+E119/$E$6 -> 0.24241596 | I119: =+E119/$D$13 -> 1.727576 | J119: =+E119/$D$14 -> 0.28831746 | K119: =+E119/$D$15 -> 0.24708167
A120: CARTERA | B120: NOMINA CARTERA | C120: 14200301 SUELDOS Y SALARIOS | D120: 0 | E120: 4994816 | F120: =IFERROR(+(E120-D120)/D120,"N/A") -> N/A | G120: =+E120/$E$5 -> 0.012767935 | H120: =+E120/$E$6 -> 0.012767935 | I120: =+E120/$D$13 -> 0.090990614 | J120: =+E120/$D$14 -> 0.015185545 | K120: =+E120/$D$15 -> 0.013013675
C121: 14200307 SUBSIDIO DE TRANSPORTE | D121: 0 | E121: 396954 | F121: =IFERROR(+(E121-D121)/D121,"N/A") -> N/A | G121: =+E121/$E$5 -> 0.0010147086 | H121: =+E121/$E$6 -> 0.0010147086 | I121: =+E121/$D$13 -> 0.007231315 | J121: =+E121/$D$14 -> 0.0012068438 | K121: =+E121/$D$15 -> 0.0010342384
C122: 14200343 VACACIONES | D122: 0 | E122: 922231 | F122: =IFERROR(+(E122-D122)/D122,"N/A") -> N/A | G122: =+E122/$E$5 -> 0.0023574412 | H122: =+E122/$E$6 -> 0.0023574412 | I122: =+E122/$D$13 -> 0.016800291 | J122: =+E122/$D$14 -> 0.002803823 | K122: =+E122/$D$15 -> 0.0024028142
C123: 14200347 PRIMA DE SERVICIO | D123: 0 | E123: 523300 | F123: =IFERROR(+(E123-D123)/D123,"N/A") -> N/A | G123: =+E123/$E$5 -> 0.0013376789 | H123: =+E123/$E$6 -> 0.0013376789 | I123: =+E123/$D$13 -> 0.0095329614 | J123: =+E123/$D$14 -> 0.0015909686 | K123: =+E123/$D$15 -> 0.0013634248
C124: 14200348 CESANTIAS | D124: 0 | E124: 523300 | F124: =IFERROR(+(E124-D124)/D124,"N/A") -> N/A | G124: =+E124/$E$5 -> 0.0013376789 | H124: =+E124/$E$6 -> 0.0013376789 | I124: =+E124/$D$13 -> 0.0095329614 | J124: =+E124/$D$14 -> 0.0015909686 | K124: =+E124/$D$15 -> 0.0013634248
C125: 14200349 INTERESES DE CESANTIAS | D125: 0 | E125: 45579 | F125: =IFERROR(+(E125-D125)/D125,"N/A") -> N/A | G125: =+E125/$E$5 -> 0.00011651074 | H125: =+E125/$E$6 -> 0.00011651074 | I125: =+E125/$D$13 -> 0.0008303131 | J125: =+E125/$D$14 -> 0.00013857206 | K125: =+E125/$D$15 -> 0.00011875318
C126: 14200356 APORTES SOBRE LA NÓMINA AL ICBF | D126: 0 | E126: 176600 | F126: =IFERROR(+(E126-D126)/D126,"N/A") -> N/A | G126: =+E126/$E$5 -> 0.00045143149 | H126: =+E126/$E$6 -> 0.00045143149 | I126: =+E126/$D$13 -> 0.003217124 | J126: =+E126/$D$14 -> 0.00053691011 | K126: =+E126/$D$15 -> 0.00046012006
C127: 14200357 APORTES SOBRE LA NÓMINA AL SENA | D127: 0 | E127: 117900 | F127: =IFERROR(+(E127-D127)/D127,"N/A") -> N/A | G127: =+E127/$E$5 -> 0.00030138037 | H127: =+E127/$E$6 -> 0.00030138037 | I127: =+E127/$D$13 -> 0.0021477855 | J127: =+E127/$D$14 -> 0.00035844678 | K127: =+E127/$D$15 -> 0.00030718095
C128: 14200358 APORTES SOBRE LA NÓMINA ARL | D128: 0 | E128: 31000 | F128: =IFERROR(+(E128-D128)/D128,"N/A") -> N/A | G128: =+E128/$E$5 -> 7.9243354e-05 | H128: =+E128/$E$6 -> 7.9243354e-05 | I128: =+E128/$D$13 -> 0.00056472731 | J128: =+E128/$D$14 -> 9.4248094e-05 | K128: =+E128/$D$15 -> 8.0768527e-05
...

Sheet WESTVILLE
A1: INFORME GENERAL DE GASTOS WESTVILLE SEPTIEMBRE 2018
A4: VENTAS | C4: RUBRO | D4: N° | E4: VALOR
C5: VENTAS DEL MES | D5: 6 | E5: 407000000
C6: a. VENTAS PROCESABLES | D6: 6 | E6: 407000000
C7: b. VENTAS NO PROCESABLES | D7: 0 | E7: 0
C8: VENTAS RADICADAS | D8: 5 | E8: 341000000
C9: VENTAS NO REGISTRABLES | D9: 0 | E9: 0
C10: RECAUDO POR VENTAS | D10: VALOR
C11: PLATA EN MESA | D11: 10875000
C12: PLATA EN MES | D12: 40000000
C13: TOTAL RECAUDO VENTAS DEL MES | D13: =+D11+D12 -> 50875000
C14: TOTAL RECAUDO CARTERA | D14: 134954502
C15: TOTAL INGRESO DEL MES | D15: =+D13+D14 -> 185829502
A16: CUENTA | D16: Mes Anterior | E16: Mes Actual | F16: Variacion | G16: %Ventas Brutas | H16: % Ventas Procesables | I16: %Recaudo Ventas Mes | J16: %Recaudo Total Mes | K16: %Recaudo Total Mes
A17: COMERCIAL | B17: NOMINA COMERCIAL | C17: 52050600 SUELDOS | D17: 15846542 | E17: 6712850 | F17: =IFERROR(+(E17-D17)/D17,"N/A") -> -0.57638392 | G17: =+E17/$E$5 -> 0.016493489 | H17: =+E17/$E$6 -> 0.016493489 | I17: =+E17/$D$13 -> 0.13194791 | J17: =+E17/$D$14 -> 0.049741579 | K17: =+E17/$D$15 -> 0.036123704
C18: 52051500 HORAS EXTRAS Y RECARGOS | D18: 182290 | E18: 113931 | F18: =IFERROR(+(E18-D18)/D18,"N/A") -> -0.37500137 | G18: =+E18/$E$5 -> 0.00027992875 | H18: =+E18/$E$6 -> 0.00027992875 | I18: =+E18/$D$13 -> 0.00223943 | J18: =+E18/$D$14 -> 0.00084421785 | K18: =+E18/$D$15 -> 0.00061309425
C19: 52052700 AUXILIO DE TRANSPORTE | D19: 1305533 | E19: 598369.5 | F19: =IFERROR(+(E19-D19)/D19,"N/A") -> -0.54166651 | G19: =+E19/$E$5 -> 0.0014701953 | H19: =+E19/$E$6 -> 0.0014701953 | I19: =+E19/$D$13 -> 0.011761563 | J19: =+E19/$D$14 -> 0.004433861 | K19: =+E19/$D$15 -> 0.0032199919
C20: 52053000 CESANTIAS | D20: 2130634.2 | E20: 1452011.5 | F20: =IFERROR(+(E20-D20)/D20,"N/A") -> -0.31850738 | G20: =+E20/$E$5 -> 0.0035675958 | H20: =+E20/$E$6 -> 0.0035675958 | I20: =+E20/$D$13 -> 0.028540767 | J20: =+E20/$D$14 -> 0.010759267 | K20: =+E20/$D$15 -> 0.0078136759
C21: 52053300 INTERESES SOBRE CESANTIAS | D21: 211672.88 | E21: 69255 | F21: =IFERROR(+(E21-D21)/D21,"N/A") -> -0.67282063 | G21: =+E21/$E$5 -> 0.00017015971 | H21: =+E21/$E$6 -> 0.00017015971 | I21: =+E21/$D$13 -> 0.0013612776 | J21: =+E21/$D$14 -> 0.00051317295 | K21: =+E21/$D$15 -> 0.00037268033
C22: 52053600 PRIMA DE SERVICIOS | D22: 1826510.9 | E22: 895921.5 | F22: =IFERROR(+(E22-D22)/D22,"N/A") -> -0.5094902 | G22: =+E22/$E$5 -> 0.0022012813 | H22: =+E22/$E$6 -> 0.0022012813 | I22: =+E22/$D$13 -> 0.017610251 | J22: =+E22/$D$14 -> 0.0066386929 | K22: =+E22/$D$15 -> 0.0048212016
C23: 52053900 VACACIONES | D23: 3139762 | E23: 1039323 | F23: =IFERROR(+(E23-D23)/D23,"N/A") -> -0.66898032 | G23: =+E23/$E$5 -> 0.0025536192 | H23: =+E23/$E$6 -> 0.0025536192 | I23: =+E23/$D$13 -> 0.020428953 | J23: =+E23/$D$14 -> 0.0077012844 | K23: =+E23/$D$15 -> 0.0055928848
C24: 52054501 AUXILIO DE VIVIENDA | D24: 1000000 | E24: 250000 | F24: =IFERROR(+(E24-D24)/D24,"N/A") -> -0.75 | G24: =+E24/$E$5 -> 0.00061425061 | H24: =+E24/$E$6 -> 0.00061425061 | I24: =+E24/$D$13 -> 0.0049140049 | J24: =+E24/$D$14 -> 0.0018524762 | K24: =+E24/$D$15 -> 0.0013453192
C25: 52054502 AUXILIO DE ALIMENTACION | D25: 250000 | E25: 250000 | F25: =IFERROR(+(E25-D25)/D25,"N/A") -> 0 | G25: =+E25/$E$5 -> 0.00061425061 | H25: =+E25/$E$6 -> 0.00061425061 | I25: =+E25/$D$13 -> 0.0049140049 | J25: =+E25/$D$14 -> 0.0018524762 | K25: =+E25/$D$15 -> 0.0013453192
C26: 52056800 APORTES A ADMINISTRADORAS DE RIESGOS PRO | D26: 225200 | E26: 121150 | F26: =IFERROR(+(E26-D26)/D26,"N/A") -> -0.46203375 | G26: =+E26/$E$5 -> 0.00029766585 | H26: =+E26/$E$6 -> 0.00029766585 | I26: =+E26/$D$13 -> 0.0023813268 | J26: =+E26/$D$14 -> 0.00089770996 | K26: =+E26/$D$15 -> 0.00065194169
C27: 52056900 APORTES A ENTIDADES PROMOTORAS DE SALUD | D27: 2230900 | E27: 1262250 | F27: =IFERROR(+(E27-D27)/D27,"N/A") -> -0.43419696 | G27: =+E27/$E$5 -> 0.0031013514 | H27: =+E27/$E$6 -> 0.0031013514 | I27: =+E27/$D$13 -> 0.024810811 | J27: =+E27/$D$14 -> 0.0093531522 | K27: =+E27/$D$15 -> 0.0067925167
C28: 52057000 APORTES A FONDOS DE PENSION Y/O CESANTIA | E28: 2786050 | F28: =IFERROR(+(E28-D28)/D28,"N/A") -> N/A | G28: =+E28/$E$5 -> 0.0068453317 | H28: =+E28/$E$6 -> 0.0068453317 | I28: =+E28/$D$13 -> 0.054762654 | J28: =+E28/$D$14 -> 0.020644365 | K28: =+E28/$D$15 -> 0.014992506
C29: 52057200 APORTES CAJAS DE COMPENSACION FAMILIAR | D29: 1343000 | E29: 725550 | F29: =IFERROR(+(E29-D29)/D29,"N/A") -> -0.45975428 | G29: =+E29/$E$5 -> 0.0017826781 | H29: =+E29/$E$6 -> 0.0017826781 | I29: =+E29/$D$13 -> 0.014261425 | J29: =+E29/$D$14 -> 0.0053762564 | K29: =+E29/$D$15 -> 0.0039043854
C30: 52057500 APORTES I C B F | D30: 532000 | E30: 260350 | F30: =IFERROR(+(E30-D30)/D30,"N/A") -> -0.5106203 | G30: =+E30/$E$5 -> 0.00063968059 | H30: =+E30/$E$6 -> 0.00063968059 | I30: =+E30/$D$13 -> 0.0051174447 | J30: =+E30/$D$14 -> 0.0019291687 | K30: =+E30/$D$15 -> 0.0014010154
C31: 52057800 SENA | D31: 354900 | E31: 173750 | F31: =IFERROR(+(E31-D31)/D31,"N/A") -> -0.51042547 | G31: =+E31/$E$5 -> 0.00042690418 | H31: =+E31/$E$6 -> 0.00042690418 | I31: =+E31/$D$13 -> 0.0034152334 | J31: =+E31/$D$14 -> 0.0012874709 | K31: =+E31/$D$15 -> 0.00093499686
C32: 52056000 INDEMNIZACIONES LABORALES | D32: 976560 | E32: 0 | F32: =IFERROR(+(E32-D32)/D32,"N/A") -> -1 | G32: =+E32/$E$5 -> 0 | H32: =+E32/$E$6 -> 0 | I32: =+E32/$D$13 -> 0 | J32: =+E32/$D$14 -> 0 | K32: =+E32/$D$15 -> 0
C33: 52058400 GASTOS MEDICOS Y DROGAS | D33: 55800 | E33: 55800 | F33: =IFERROR(+(E33-D33)/D33,"N/A") -> 0 | G33: =+E33/$E$5 -> 0.00013710074 | H33: =+E33/$E$6 -> 0.00013710074 | I33: =+E33/$D$13 -> 0.0010968059 | J33: =+E33/$D$14 -> 0.00041347268 | K33: =+E33/$D$15 -> 0.00030027525
C34: 52157000 IVA DESCONTABLE | D34: 25840 | E34: 17765 | F34: =IFERROR(+(E34-D34)/D34,"N/A") -> -0.3125 | G34: =+E34/$E$5 -> 4.3648649e-05 | H34: =+E34/$E$6 -> 4.3648649e-05 | I34: =+E34/$D$13 -> 0.00034918919 | J34: =+E34/$D$14 -> 0.00013163696 | K34: =+E34/$D$15 -> 9.5598384e-05
C35: TOTAL NOMINA COMERCIAL | D35: 36660345 | E35: 16784326 | F35: =IFERROR(+(E35-D35)/D35,"N/A") -> -0.54216671 | G35: =+E35/$E$5 -> 0.041239131 | H35: =+E35/$E$6 -> 0.041239131 | I35: =+E35/$D$13 -> 0.32991305 | J35: =+E35/$D$14 -> 0.12437026 | K35: =+E35/$D$15 -> 0.090321108
B36: OPERACIÓN COMERCIAL | C36: 14400202 G.T.T. ASESORES | D36: =+VLOOKUP(C36,Hoja2!$A$105:$F$143,6,FALSE) -> 7230000 | E36: 6885000 | F36: =IFERROR(+(E36-D36)/D36,"N/A") -> -0.047717842 | G36: =+E36/$E$5 -> 0.016916462 | H36: =+E36/$E$6 -> 0.016916462 | I36: =+E36/$D$13 -> 0.1353317 | J36: =+E36/$D$14 -> 0.051017194 | K36: =+E36/$D$15 -> 0.037050091
C37: 14400204 EVENTOS COMERCIALES | D37: =+VLOOKUP(C37,Hoja2!$A$105:$F$143,6,FALSE) -> 9782460 | E37: =13381632+5383590 -> 18765222 | F37: =IFERROR(+(E37-D37)/D37,"N/A") -> 0.91825185 | G37: =+E37/$E$5 -> 0.046106197 | H37: =+E37/$E$6 -> 0.046106197 | I37: =+E37/$D$13 -> 0.36884957 | J37: =+E37/$D$14 -> 0.13904851 | K37: =+E37/$D$15 -> 0.10098086
C38: 14400205 ALIMENTOS | D38: =+VLOOKUP(C38,Hoja2!$A$105:$F$143,6,FALSE) -> 0 | E38: 223900 | F38: =IFERROR(+(E38-D38)/D38,"N/A") -> N/A | G38: =+E38/$E$5 -> 0.00055012285 | H38: =+E38/$E$6 -> 0.00055012285 | I38: =+E38/$D$13 -> 0.0044009828 | J38: =+E38/$D$14 -> 0.0016590777 | K38: =+E38/$D$15 -> 0.0012048679
C39: 14400209 CAPACITACION ASESORES COMERCIALES | D39: =+VLOOKUP(C39,Hoja2!$A$105:$F$143,6,FALSE) -> 0 | E39: 1414000 | F39: =IFERROR(+(E39-D39)/D39,"N/A") -> N/A | G39: =+E39/$E$5 -> 0.0034742015 | H39: =+E39/$E$6 -> 0.0034742015 | I39: =+E39/$D$13 -> 0.027793612 | J39: =+E39/$D$14 -> 0.010477605 | K39: =+E39/$D$15 -> 0.0076091255
C40: 14400210 ALIMENTACION PERSONAL EN EVENTO | D40: =+VLOOKUP(C40,Hoja2!$A$105:$F$143,6,FALSE) -> 938796 | E40: 444370 | F40: =IFERROR(+(E40-D40)/D40,"N/A") -> -0.52665968 | G40: =+E40/$E$5 -> 0.0010918182 | H40: =+E40/$E$6 -> 0.0010918182 | I40: =+E40/$D$13 -> 0.0087345455 | J40: =+E40/$D$14 -> 0.0032927394 | K40: =+E40/$D$15 -> 0.002391278
C41: 14400213 TRANSPORTES A EVENTOS | D41: =+VLOOKUP(C41,Hoja2!$A$105:$F$143,6,FALSE) -> 394000 | E41: 37000 | F41: =IFERROR(+(E41-D41)/D41,"N/A") -> -0.90609137 | G41: =+E41/$E$5 -> 9.0909091e-05 | H41: =+E41/$E$6 -> 9.0909091e-05 | I41: =+E41/$D$13 -> 0.00072727273 | J41: =+E41/$D$14 -> 0.00027416647 | K41: =+E41/$D$15 -> 0.00019910724
C42: 14400214 BONIFICACION SPIFF | D42: =+VLOOKUP(C42,Hoja2!$A$105:$F$143,6,FALSE) -> 100000 | E42: 400000 | F42: =IFERROR(+(E42-D42)/D42,"N/A") -> 3 | G42: =+E42/$E$5 -> 0.00098280098 | H42: =+E42/$E$6 -> 0.00098280098 | I42: =+E42/$D$13 -> 0.0078624079 | J42: =+E42/$D$14 -> 0.0029639619 | K42: =+E42/$D$15 -> 0.0021525107
C43: 14400217 QS POR JEFE DE PROMOCIÓN | D43: =+VLOOKUP(C43,Hoja2!$A$105:$F$143,6,FALSE) -> 192000 | E43: 312000 | F43: =IFERROR(+(E43-D43)/D43,"N/A") -> 0.625 | G43: =+E43/$E$5 -> 0.00076658477 | H43: =+E43/$E$6 -> 0.00076658477 | I43: =+E43/$D$13 -> 0.0061326781 | J43: =+E43/$D$14 -> 0.0023118903 | K43: =+E43/$D$15 -> 0.0016789584
C44: 14400219 HOSSTES | D44: =+VLOOKUP(C44,Hoja2!$A$105:$F$143,6,FALSE) -> 610000 | E44: 480617 | F44: =IFERROR(+(E44-D44)/D44,"N/A") -> -0.21210328 | G44: =+E44/$E$5 -> 0.0011808771 | H44: =+E44/$E$6 -> 0.0011808771 | I44: =+E44/$D$13 -> 0.0094470172 | J44: =+E44/$D$14 -> 0.0035613262 | K44: =+E44/$D$15 -> 0.0025863331
C45: 14400222 PAPELERIA PARA PROMOCION/VENTAS | D45: =+VLOOKUP(C45,Hoja2!$A$105:$F$143,6,FALSE) -> 54950 | E45: 807000 | F45: =IFERROR(+(E45-D45)/D45,"N/A") -> 13.686078 | G45: =+E45/$E$5 -> 0.001982801 | H45: =+E45/$E$6 -> 0.001982801 | I45: =+E45/$D$13 -> 0.015862408 | J45: =+E45/$D$14 -> 0.0059797931 | K45: =+E45/$D$15 -> 0.0043426904
C46: 14400226 ANTICIPOS DE COMISION | D46: =+VLOOKUP(C46,Hoja2!$A$105:$F$143,6,FALSE) -> 200000 | E46: 200000 | F46: =IFERROR(+(E46-D46)/D46,"N/A") -> 0 | G46: =+E46/$E$5 -> 0.00049140049 | H46: =+E46/$E$6 -> 0.00049140049 | I46: =+E46/$D$13 -> 0.0039312039 | J46: =+E46/$D$14 -> 0.0014819809 | K46: =+E46/$D$15 -> 0.0010762554
C47: 14400233 BONIFICACIÓN TLMK | D47: =+VLOOKUP(C47,Hoja2!$A$105:$F$143,6,FALSE) -> 793500 | E47: 288000 | F47: =IFERROR(+(E47-D47)/D47,"N/A") -> -0.63705104 | G47: =+E47/$E$5 -> 0.00070761671 | H47: =+E47/$E$6 -> 0.00070761671 | I47: =+E47/$D$13 -> 0.0056609337 | J47: =+E47/$D$14 -> 0.0021340526 | K47: =+E47/$D$15 -> 0.0015498077
C48: 14400244 IVA DESCONTABLE MAYOR VALOR AL COSTO O GASTO | D48: =+VLOOKUP(C48,Hoja2!$A$105:$F$143,6,FALSE) -> 0 | E48: 128767 | F48: =IFERROR(+(E48-D48)/D48,"N/A") -> N/A | G48: =+E48/$E$5 -> 0.00031638084 | H48: =+E48/$E$6 -> 0.00031638084 | I48: =+E48/$D$13 -> 0.0025310467 | J48: =+E48/$D$14 -> 0.0009541512 | K48: =+E48/$D$15 -> 0.00069293088
C49: 14400245 IMPUESTO AL CONSUMO | D49: =+VLOOKUP(C49,Hoja2!$A$105:$F$143,6,FALSE) -> 0 | E49: 984149 | F49: =IFERROR(+(E49-D49)/D49,"N/A") -> N/A | G49: =+E49/$E$5 -> 0.0024180565 | H49: =+E49/$E$6 -> 0.0024180565 | I49: =+E49/$D$13 -> 0.019344452 | J49: =+E49/$D$14 -> 0.0072924503 | K49: =+E49/$D$15 -> 0.0052959782
C50: TOTAL OPERACION COMERCIAL | D50: =SUM(D36:D49) -> 20295706 | E50: =SUM(E36:E49) -> 31370025 | F50: =+(E50-D50)/D50 -> 0.54564838 | G50: =+E50/$E$5 -> 0.077076229 | H50: =+E50/$E$6 -> 0.077076229 | I50: =+E50/$D$13 -> 0.61660983 | J50: =+E50/$D$14 -> 0.2324489 | K50: =+E50/$D$15 -> 0.16881079
B51: TOTAL OPERACIÓN COMERCIAL ANTES DE COMISIONES | D51: =+D35+D50 -> 56956051 | E51: =+E35+E50 -> 48154352 | F51: =+(E51-D51)/D51 -> -0.15453493 | G51: =+E51/$E$5 -> 0.11831536 | H51: =+E51/$E$6 -> 0.11831536 | I51: =+E51/$D$13 -> 0.94652288 | J51: =+E51/$D$14 -> 0.35681916 | K51: =+E51/$D$15 -> 0.2591319
B52: COMIS | C52: 14400227 COMISIONES COMERCIALES POR VENTAS DEL MES | D52: 968000 | E52: 5295500 | F52: =IFERROR(+(E52-D52)/D52,"N/A") -> 4.4705579 | G52: =+E52/$E$5 -> 0.013011057 | H52: =+E52/$E$6 -> 0.013011057 | I52: =+E52/$D$13 -> 0.10408845 | J52: =+E52/$D$14 -> 0.03923915 | K52: =+E52/$D$15 -> 0.028496552
C53: 14400227 COMISIONES COMERCIALES POR VENTAS DE OTROS MESES | D53: 29045648 | E53: 14822564 | F53: =IFERROR(+(E53-D53)/D53,"N/A") -> -0.48968038 | G53: =+E53/$E$5 -> 0.036419076 | H53: =+E53/$E$6 -> 0.036419076 | I53: =+E53/$D$13 -> 0.29135261 | J53: =+E53/$D$14 -> 0.10983379 | K53: =+E53/$D$15 -> 0.079764321
C54: TOTAL COMISIONES POR VENTAS | D54: =SUM(D52:D53) -> 30013648 | E54: =SUM(E52:E53) -> 20118064 | F54: =IFERROR(+(E54-D54)/D54,"N/A") -> -0.32970281 | G54: =+E54/$E$5 -> 0.049430133 | H54: =+E54/$E$6 -> 0.049430133 | I54: =+E54/$D$13 -> 0.39544106 | J54: =+E54/$D$14 -> 0.14907294 | K54: =+E54/$D$15 -> 0.10826087
A55: ADMINISRTRACION | B55: NOMINA ADMINISTRACION | C55: 14200101 SUELDOS Y SALARIOS | D55: =+VLOOKUP(C55,Hoja2!$A$3:$F$20,6,FALSE) -> 3320392 | E55: 3320392 | F55: =IFERROR(+(E55-D55)/D55,"N/A") -> 0 | G55: =+E55/$E$5 -> 0.0081582113 | H55: =+E55/$E$6 -> 0.0081582113 | I55: =+E55/$D$13 -> 0.06526569 | J55: =+E55/$D$14 -> 0.024603788 | K55: =+E55/$D$15 -> 0.017867949
C56: 14200107 SUBSIDIO DE TRANSPORTE | D56: =+VLOOKUP(C56,Hoja2!$A$3:$F$20,6,FALSE) -> 264636 | E56: 264636 | F56: =IFERROR(+(E56-D56)/D56,"N/A") -> 0 | G56: =+E56/$E$5 -> 0.0006502113 | H56: =+E56/$E$6 -> 0.0006502113 | I56: =+E56/$D$13 -> 0.0052016904 | J56: =+E56/$D$14 -> 0.0019609275 | K56: =+E56/$D$15 -> 0.0014240796
C57: 14200116 BONIFICACIÓN NO SALARIAL | D57: =+VLOOKUP(C57,Hoja2!$A$3:$F$20,6,FALSE) -> 450000 | E57: 450000 | F57: =IFERROR(+(E57-D57)/D57,"N/A") -> 0 | G57: =+E57/$E$5 -> 0.0011056511 | H57: =+E57/$E$6 -> 0.0011056511 | I57: =+E57/$D$13 -> 0.0088452088 | J57: =+E57/$D$14 -> 0.0033344571 | K57: =+E57/$D$15 -> 0.0024215746
C58: 14200143 VACACIONES | D58: =+VLOOKUP(C58,Hoja2!$A$3:$F$20,6,FALSE) -> 130765 | E58: 168335 | F58: =IFERROR(+(E58-D58)/D58,"N/A") -> 0.2873093 | G58: =+E58/$E$5 -> 0.00041359951 | H58: =+E58/$E$6 -> 0.00041359951 | I58: =+E58/$D$13 -> 0.0033087961 | J58: =+E58/$D$14 -> 0.0012473463 | K58: =+E58/$D$15 -> 0.00090585724
C59: 14200147 PRIMA DE SERVICIO | D59: =+VLOOKUP(C59,Hoja2!$A$3:$F$20,6,FALSE) -> 298753 | E59: 298750 | F59: =IFERROR(+(E59-D59)/D59,"N/A") -> -1.004174e-05 | G59: =+E59/$E$5 -> 0.00073402948 | H59: =+E59/$E$6 -> 0.00073402948 | I59: =+E59/$D$13 -> 0.0058722359 | J59: =+E59/$D$14 -> 0.002213709 | K59: =+E59/$D$15 -> 0.0016076565
C60: 14200148 CESANTIAS | D60: =+VLOOKUP(C60,Hoja2!$A$3:$F$20,6,FALSE) -> 298753 | E60: 298750 | F60: =IFERROR(+(E60-D60)/D60,"N/A") -> -1.004174e-05 | G60: =+E60/$E$5 -> 0.00073402948 | H60: =+E60/$E$6 -> 0.00073402948 | I60: =+E60/$D$13 -> 0.0058722359 | J60: =+E60/$D$14 -> 0.002213709 | K60: =+E60/$D$15 -> 0.0016076565
C61: 14200149 INTERESES DE CESANTIAS | D61: =+VLOOKUP(C61,Hoja2!$A$3:$F$20,6,FALSE) -> 35853 | E61: 14899 | F61: =IFERROR(+(E61-D61)/D61,"N/A") -> -0.58444203 | G61: =+E61/$E$5 -> 3.660688e-05 | H61: =+E61/$E$6 -> 3.660688e-05 | I61: =+E61/$D$13 -> 0.00029285504 | J61: =+E61/$D$14 -> 0.00011040017 | K61: =+E61/$D$15 -> 8.0175644e-05
C62: 14200156 APORTES SOBRE LA NÓMINA AL ICBF | D62: =+VLOOKUP(C62,Hoja2!$A$3:$F$20,6,FALSE) -> 99800 | E62: 49900 | F62: =IFERROR(+(E62-D62)/D62,"N/A") -> -0.5 | G62: =+E62/$E$5 -> 0.00012260442 | H62: =+E62/$E$6 -> 0.00012260442 | I62: =+E62/$D$13 -> 0.00098083538 | J62: =+E62/$D$14 -> 0.00036975425 | K62: =+E62/$D$15 -> 0.00026852572
C63: 14200157 APORTES SOBRE LA NÓMINA AL SENA | D63: =+VLOOKUP(C63,Hoja2!$A$3:$F$20,6,FALSE) -> 66600 | E63: 33400 | F63: =IFERROR(+(E63-D63)/D63,"N/A") -> -0.4984985 | G63: =+E63/$E$5 -> 8.2063882e-05 | H63: =+E63/$E$6 -> 8.2063882e-05 | I63: =+E63/$D$13 -> 0.00065651106 | J63: =+E63/$D$14 -> 0.00024749082 | K63: =+E63/$D$15 -> 0.00017973465
C64: 14200158 APORTES SOBRE LA NÓMINA ARL | D64: =+VLOOKUP(C64,Hoja2!$A$3:$F$20,6,FALSE) -> 17500 | E64: 8800 | F64: =IFERROR(+(E64-D64)/D64,"N/A") -> -0.49714286 | G64: =+E64/$E$5 -> 2.1621622e-05 | H64: =+E64/$E$6 -> 2.1621622e-05 | I64: =+E64/$D$13 -> 0.00017297297 | J64: =+E64/$D$14 -> 6.5207161e-05 | K64: =+E64/$D$15 -> 4.7355236e-05
C65: 14200159 APORTES SOBRE LA NÓMINA SALUD-EPS | D65: =+VLOOKUP(C65,Hoja2!$A$3:$F$20,6,FALSE) -> 281900 | E65: 141000 | F65: =IFERROR(+(E65-D65)/D65,"N/A") -> -0.49982263 | G65: =+E65/$E$5 -> 0.00034643735 | H65: =+E65/$E$6 -> 0.00034643735 | I65: =+E65/$D$13 -> 0.0027714988 | J65: =+E65/$D$14 -> 0.0010447966 | K65: =+E65/$D$15 -> 0.00075876004
C66: 14200160 APORTES SOBRE LA NÓMINA PENSIONES Y/O CESANTÍAS | D66: =+VLOOKUP(C66,Hoja2!$A$3:$F$20,6,FALSE) -> 398200 | E66: 199200 | F66: =IFERROR(+(E66-D66)/D66,"N/A") -> -0.49974887 | G66: =+E66/$E$5 -> 0.00048943489 | H66: =+E66/$E$6 -> 0.00048943489 | I66: =+E66/$D$13 -> 0.0039154791 | J66: =+E66/$D$14 -> 0.001476053 | K66: =+E66/$D$15 -> 0.0010719504
C67: 14200161 APORTES SOBRE LA NÓMINA APORTES CAJAS DE COMPENSAC | D67: =+VLOOKUP(C67,Hoja2!$A$3:$F$20,6,FALSE) -> 133000 | E67: 66600 | F67: =IFERROR(+(E67-D67)/D67,"N/A") -> -0.49924812 | G67: =+E67/$E$5 -> 0.00016363636 | H67: =+E67/$E$6 -> 0.00016363636 | I67: =+E67/$D$13 -> 0.0013090909 | J67: =+E67/$D$14 -> 0.00049349965 | K67: =+E67/$D$15 -> 0.00035839304
C68: TOTAL NOMINA ADMINISTRACION | D68: =SUM(D55:D67) -> 5796152 | E68: =SUM(E55:E67) -> 5314662 | F68: =IFERROR(+(E68-D68)/D68,"N/A") -> -0.08307063 | G68: =+E68/$E$5 -> 0.013058138 | H68: =+E68/$E$6 -> 0.013058138 | I68: =+E68/$D$13 -> 0.1044651 | J68: =+E68/$D$14 -> 0.039381139 | K68: =+E68/$D$15 -> 0.028599668
B69: OPERACIÓN ADMINISTRACION | C69: 14400117 GASTOS LEGALES GASTOS NOTARIALES | D69: =+VLOOKUP(C69,Hoja2!$A$24:$F$74,6,FALSE) -> 0 | E69: 73400 | F69: =IFERROR(+(E69-D69)/D69,"N/A") -> N/A | G69: =+E69/$E$5 -> 0.00018034398 | H69: =+E69/$E$6 -> 0.00018034398 | I69: =+E69/$D$13 -> 0.0014427518 | J69: =+E69/$D$14 -> 0.00054388701 | K69: =+E69/$D$15 -> 0.00039498572
C70: 14400118 GASTOS LEGALES TRAMITES Y PERMISOS | D70: =+VLOOKUP(C70,Hoja2!$A$24:$F$74,6,FALSE) -> 1000000 | E70: 0 | F70: =IFERROR(+(E70-D70)/D70,"N/A") -> -1 | G70: =+E70/$E$5 -> 0 | H70: =+E70/$E$6 -> 0 | I70: =+E70/$D$13 -> 0 | J70: =+E70/$D$14 -> 0 | K70: =+E70/$D$15 -> 0
C71: 14400122 MANTENIMIENTO DE REDES Y EQUIPO DE COMPUTO | D71: =+VLOOKUP(C71,Hoja2!$A$24:$F$74,6,FALSE) -> 0 | E71: 2300000 | F71: =IFERROR(+(E71-D71)/D71,"N/A") -> N/A | G71: =+E71/$E$5 -> 0.0056511057 | H71: =+E71/$E$6 -> 0.0056511057 | I71: =+E71/$D$13 -> 0.045208845 | J71: =+E71/$D$14 -> 0.017042781 | K71: =+E71/$D$15 -> 0.012376937
C72: 14400131 DIVERSOS ASEO Y CAFETERIA | D72: =+VLOOKUP(C72,Hoja2!$A$24:$F$74,6,FALSE) -> 0 | E72: 152655 | F72: =IFERROR(+(E72-D72)/D72,"N/A") -> N/A | G72: =+E72/$E$5 -> 0.00037507371 | H72: =+E72/$E$6 -> 0.00037507371 | I72: =+E72/$D$13 -> 0.0030005897 | J72: =+E72/$D$14 -> 0.001131159 | K72: =+E72/$D$15 -> 0.00082147882
C73: 14400132 DIVERSOS MENSAJERIA-TRANSPORTE | D73: =+VLOOKUP(C73,Hoja2!$A$24:$F$74,6,FALSE) -> 75000 | E73: 4350 | F73: =IFERROR(+(E73-D73)/D73,"N/A") -> -0.942 | G73: =+E73/$E$5 -> 1.0687961e-05 | H73: =+E73/$E$6 -> 1.0687961e-05 | I73: =+E73/$D$13 -> 8.5503686e-05 | J73: =+E73/$D$14 -> 3.2233085e-05 | K73: =+E73/$D$15 -> 2.3408554e-05
C74: 14400136 IMPUESTOS INDUSTRIA Y COMERCIO | D74: =+VLOOKUP(C74,Hoja2!$A$24:$F$74,6,FALSE) -> 33000 | E74: 33000 | F74: =IFERROR(+(E74-D74)/D74,"N/A") -> 0 | G74: =+E74/$E$5 -> 8.1081081e-05 | H74: =+E74/$E$6 -> 8.1081081e-05 | I74: =+E74/$D$13 -> 0.00064864865 | J74: =+E74/$D$14 -> 0.00024452686 | K74: =+E74/$D$15 -> 0.00017758214
C75: 14400144 GASTOS BANCARIOS COMISIONES | D75: =+VLOOKUP(C75,Hoja2!$A$24:$F$74,6,FALSE) -> 11840 | E75: 1123924 | F75: =IFERROR(+(E75-D75)/D75,"N/A") -> 93.926014 | G75: =+E75/$E$5 -> 0.002761484 | H75: =+E75/$E$6 -> 0.002761484 | I75: =+E75/$D$13 -> 0.022091872 | J75: =+E75/$D$14 -> 0.0083281697 | K75: =+E75/$D$15 -> 0.0060481462
C76: 14400145 GASTOS BANCARIOS INTERESES | D76: =+VLOOKUP(C76,Hoja2!$A$24:$F$74,6,FALSE) -> 45.69 | E76: 8 | F76: =IFERROR(+(E76-D76)/D76,"N/A") -> -0.82490698 | G76: =+E76/$E$5 -> 1.965602e-08 | H76: =+E76/$E$6 -> 1.965602e-08 | I76: =+E76/$D$13 -> 1.5724816e-07 | J76: =+E76/$D$14 -> 5.9279238e-08 | K76: =+E76/$D$15 -> 4.3050215e-08
C77: 14400146 GASTOS BANCARIOS GMF | D77: =+VLOOKUP(C77,Hoja2!$A$24:$F$74,6,FALSE) -> 263898.58 | E77: 547126 | F77: =IFERROR(+(E77-D77)/D77,"N/A") -> 1.0732434 | G77: =+E77/$E$5 -> 0.0013442899 | H77: =+E77/$E$6 -> 0.0013442899 | I77: =+E77/$D$13 -> 0.010754319 | J77: =+E77/$D$14 -> 0.0040541515 | K77: =+E77/$D$15 -> 0.0029442365
C78: 14400147 IVA DESCONTABLE MAYOR VALOR AL COSTO O GASTO | D78: =+VLOOKUP(C78,Hoja2!$A$24:$F$74,6,FALSE) -> 169150 | E78: 113992 | F78: =IFERROR(+(E78-D78)/D78,"N/A") -> -0.32608927 | G78: =+E78/$E$5 -> 0.00028007862 | H78: =+E78/$E$6 -> 0.00028007862 | I78: =+E78/$D$13 -> 0.002240629 | J78: =+E78/$D$14 -> 0.00084466986 | K78: =+E78/$D$15 -> 0.00061342251
C79: 14400171 GASTO ASOCIACION FENALCO | D79: =+VLOOKUP(C79,Hoja2!$A$24:$F$74,6,FALSE) -> 0 | E79: 325129 | F79: =IFERROR(+(E79-D79)/D79,"N/A") -> N/A | G79: =+E79/$E$5 -> 0.00079884275 | H79: =+E79/$E$6 -> 0.00079884275 | I79: =+E79/$D$13 -> 0.006390742 | J79: =+E79/$D$14 -> 0.0024091749 | K79: =+E79/$D$15 -> 0.0017496092
C80: 14400172 REFRIGERIOS ADMINSTRATIVOS | D80: 0 | E80: 10000 | F80: =IFERROR(+(E80-D80)/D80,"N/A") -> N/A | G80: =+E80/$E$5 -> 2.4570025e-05 | H80: =+E80/$E$6 -> 2.4570025e-05 | I80: =+E80/$D$13 -> 0.0001965602 | J80: =+E80/$D$14 -> 7.4099047e-05 | K80: =+E80/$D$15 -> 5.3812769e-05
C81: 14400173 INTERESES PRESTAMOS A TERCEROS | D81: =+VLOOKUP(C81,Hoja2!$A$24:$F$74,6,FALSE) -> 0 | E81: 8535786 | F81: =IFERROR(+(E81-D81)/D81,"N/A") -> N/A | G81: =+E81/$E$5 -> 0.020972447 | H81: =+E81/$E$6 -> 0.020972447 | I81: =+E81/$D$13 -> 0.16777958 | J81: =+E81/$D$14 -> 0.063249361 | K81: =+E81/$D$15 -> 0.045933428
C82: 14400174 ARRENDAMIENTO EQUIPOS ELECTRONICOS | D82: =+VLOOKUP(C82,Hoja2!$A$24:$F$74,6,FALSE) -> 0 | E82: 103491 | F82: =IFERROR(+(E82-D82)/D82,"N/A") -> N/A | G82: =+E82/$E$5 -> 0.00025427764 | H82: =+E82/$E$6 -> 0.00025427764 | I82: =+E82/$D$13 -> 0.0020342211 | J82: =+E82/$D$14 -> 0.00076685845 | K82: =+E82/$D$15 -> 0.00055691372
C83: TOTAL GASTO ADMINISTRACION | D83: =SUM(D69:D82) -> 1552934.3 | E83: =SUM(E69:E82) -> 13322861 | F83: =IFERROR(+(E83-D83)/D83,"N/A") -> 7.5791532 | G83: =+E83/$E$5 -> 0.032734302 | H83: =+E83/$E$6 -> 0.032734302 | I83: =+E83/$D$13 -> 0.26187442 | J83: =+E83/$D$14 -> 0.09872113 | K83: =+E83/$D$15 -> 0.071694004
B84: TOTAL OPERACIÓN ADMINISTRACION | D84: =+D83+D68 -> 7349086.3 | E84: =+E83+E68 -> 18637523 | F84: =IFERROR(+(E84-D84)/D84,"N/A") -> 1.5360327 | G84: =+E84/$E$5 -> 0.04579244 | H84: =+E84/$E$6 -> 0.04579244 | I84: =+E84/$D$13 -> 0.36633952 | J84: =+E84/$D$14 -> 0.13810227 | K84: =+E84/$D$15 -> 0.10029367
A85: CARTERA | B85: NOMINA CARTERA | C85: 14200301 SUELDOS Y SALARIOS | D85: 0 | E85: 1248704 | F85: =IFERROR(+(E85-D85)/D85,"N/A") -> N/A | G85: =+E85/$E$5 -> 0.0030680688 | H85: =+E85/$E$6 -> 0.0030680688 | I85: =+E85/$D$13 -> 0.02454455 | J85: =+E85/$D$14 -> 0.0092527777 | K85: =+E85/$D$15 -> 0.0067196219
C86: 14200307 SUBSIDIO DE TRANSPORTE | D86: 0 | E86: 99238.5 | F86: =IFERROR(+(E86-D86)/D86,"N/A") -> N/A | G86: =+E86/$E$5 -> 0.00024382924 | H86: =+E86/$E$6 -> 0.00024382924 | I86: =+E86/$D$13 -> 0.0019506339 | J86: =+E86/$D$14 -> 0.00073534783 | K86: =+E86/$D$15 -> 0.00053402984
C87: 14200343 VACACIONES | D87: 0 | E87: 230557.75 | F87: =IFERROR(+(E87-D87)/D87,"N/A") -> N/A | G87: =+E87/$E$5 -> 0.00056648096 | H87: =+E87/$E$6 -> 0.00056648096 | I87: =+E87/$D$13 -> 0.0045318477 | J87: =+E87/$D$14 -> 0.001708411 | K87: =+E87/$D$15 -> 0.0012406951
C88: 14200347 PRIMA DE SERVICIO | D88: 0 | E88: 130825 | F88: =IFERROR(+(E88-D88)/D88,"N/A") -> N/A | G88: =+E88/$E$5 -> 0.00032143735 | H88: =+E88/$E$6 -> 0.00032143735 | I88: =+E88/$D$13 -> 0.0025714988 | J88: =+E88/$D$14 -> 0.00096940078 | K88: =+E88/$D$15 -> 0.00070400555
C89: 14200348 CESANTIAS | D89: 0 | E89: 130825 | F89: =IFERROR(+(E89-D89)/D89,"N/A") -> N/A | G89: =+E89/$E$5 -> 0.00032143735 | H89: =+E89/$E$6 -> 0.00032143735 | I89: =+E89/$D$13 -> 0.0025714988 | J89: =+E89/$D$14 -> 0.00096940078 | K89: =+E89/$D$15 -> 0.00070400555
C90: 14200349 INTERESES DE CESANTIAS | D90: 0 | E90: 11394.75 | F90: =IFERROR(+(E90-D90)/D90,"N/A") -> N/A | G90: =+E90/$E$5 -> 2.7996929e-05 | H90: =+E90/$E$6 -> 2.7996929e-05 | I90: =+E90/$D$13 -> 0.00022397543 | J90: =+E90/$D$14 -> 8.4434012e-05 | K90: =+E90/$D$15 -> 6.1318305e-05
C91: 14200356 APORTES SOBRE LA NÓMINA AL ICBF | D91: 0 | E91: 44150 | F91: =IFERROR(+(E91-D91)/D91,"N/A") -> N/A | G91: =+E91/$E$5 -> 0.00010847666 | H91: =+E91/$E$6 -> 0.00010847666 | I91: =+E91/$D$13 -> 0.00086781327 | J91: =+E91/$D$14 -> 0.00032714729 | K91: =+E91/$D$15 -> 0.00023758337
C92: 14200357 APORTES SOBRE LA NÓMINA AL SENA | D92: 0 | E92: 29475 | F92: =IFERROR(+(E92-D92)/D92,"N/A") -> N/A | G92: =+E92/$E$5 -> 7.2420147e-05 | H92: =+E92/$E$6 -> 7.2420147e-05 | I92: =+E92/$D$13 -> 0.00057936118 | J92: =+E92/$D$14 -> 0.00021840694 | K92: =+E92/$D$15 -> 0.00015861314
C93: 14200358 APORTES SOBRE LA NÓMINA ARL | D93: 0 | E93: 7750 | F93: =IFERROR(+(E93-D93)/D93,"N/A") -> N/A | G93: =+E93/$E$5 -> 1.9041769e-05 | H93: =+E93/$E$6 -> 1.9041769e-05 | I93: =+E93/$D$13 -> 0.00015233415 | J93: =+E93/$D$14 -> 5.7426762e-05 | K93: =+E93/$D$15 -> 4.1704896e-05
C94: 14200359 APORTES SOBRE LA NÓMINA SALUD-EPS | D94: 0 | E94: 124950 | F94: =IFERROR(+(E94-D94)/D94,"N/A") -> N/A | G94: =+E94/$E$5 -> 0.00030700246 | H94: =+E94/$E$6 -> 0.00030700246 | I94: =+E94/$D$13 -> 0.0024560197 | J94: =+E94/$D$14 -> 0.00092586759 | K94: =+E94/$D$15 -> 0.00067239054
C95: 14200360 APORTES SOBRE LA NÓMINA PENSIONES Y/O CESANTÍAS | D95: 0 | E95: 148025 | F95: =IFERROR(+(E95-D95)/D95,"N/A") -> N/A | G95: =+E95/$E$5 -> 0.00036369779 | H95: =+E95/$E$6 -> 0.00036369779 | I95: =+E95/$D$13 -> 0.0029095823 | J95: =+E95/$D$14 -> 0.0010968511 | K95: =+E95/$D$15 -> 0.00079656351
C96: 14200361 APORTES SOBRE LA NÓMINA APORTES CAJAS DE COMPENSAC | D96: 0 | E96: 58875 | F96: =IFERROR(+(E96-D96)/D96,"N/A") -> N/A | G96: =+E96/$E$5 -> 0.00014465602 | H96: =+E96/$E$6 -> 0.00014465602 | I96: =+E96/$D$13 -> 0.0011572482 | J96: =+E96/$D$14 -> 0.00043625814 | K96: =+E96/$D$15 -> 0.00031682268
C97: 52054801 BONIFICACIONES NO SALARIALES | D97: 0 | E97: 50000 | F97: =IFERROR(+(E97-D97)/D97,"N/A") -> N/A | G97: =+E97/$E$5 -> 0.00012285012 | H97: =+E97/$E$6 -> 0.00012285012 | I97: =+E97/$D$13 -> 0.00098280098 | J97: =+E97/$D$14 -> 0.00037049524 | K97: =+E97/$D$15 -> 0.00026906384
C98: TOTAL NOMINA CARTERA | D98: =SUM(D85:D97) -> 0 | E98: =SUM(E85:E97) -> 2314770 | F98: =IFERROR(+(E98-D98)/D98,"N/A") -> N/A | G98: =+E98/$E$5 -> 0.0056873956 | H98: =+E98/$E$6 -> 0.0056873956 | I98: =+E98/$D$13 -> 0.045499165 | J98: =+E98/$D$14 -> 0.017152225 | K98: =+E98/$D$15 -> 0.012456418
B99: OPERAC | C99: 14400402 CASH OUT | D99: 0 | E99: 709188 | F99: =IFERROR(+(E99-D99)/D99,"N/A") -> N/A | G99: =+E99/$E$5 -> 0.0017424767 | H99: =+E99/$E$6 -> 0.0017424767 | I99: =+E99/$D$13 -> 0.013939813 | J99: =+E99/$D$14 -> 0.0052550155 | K99: =+E99/$D$15 -> 0.003816337
C100: 14400403 BONIFICACIONES | D100: 0 | E100: 437272 | F100: =IFERROR(+(E100-D100)/D100,"N/A") -> N/A | G100: =+E100/$E$5 -> 0.0010743784 | H100: =+E100/$E$6 -> 0.0010743784 | I100: =+E100/$D$13 -> 0.008595027 | J100: =+E100/$D$14 -> 0.0032401439 | K100: =+E100/$D$15 -> 0.0023530817
C101: TOTAL OPERACION CARTERA | D101: =SUM(D99:D100) -> 0 | E101: =SUM(E99:E100) -> 1146460 | F101: =IFERROR(+(E101-D101)/D101,"N/A") -> N/A | G101: =+E101/$E$5 -> 0.002816855 | H101: =+E101/$E$6 -> 0.002816855 | I101: =+E101/$D$13 -> 0.02253484 | J101: =+E101/$D$14 -> 0.0084951594 | K101: =+E101/$D$15 -> 0.0061694187
B102: TOTAL OPERACIÓN CARTERA | D102: =+D101+D98 -> 0 | E102: =+E101+E98 -> 3461230 | F102: =IFERROR(+(E102-D102)/D102,"N/A") -> N/A | G102: =+E102/$E$5 -> 0.0085042506 | H102: =+E102/$E$6 -> 0.0085042506 | I102: =+E102/$D$13 -> 0.068034005 | J102: =+E102/$D$14 -> 0.025647384 | K102: =+E102/$D$15 -> 0.018625837
...

Sheet Hoja3
A1: Expr1 | B1: Expr2 | C1: SumaDeSumaDeVALOR
A2: G1 | B2: NOMINA COMERCIAL | C2: 33568653
A3: Expr1 | B3: Expr2 | C3: SumaDeSumaDeVALOR | D3: EMPRESA
A4: G2 | B4: GASTO OPERACIONAL COMERCIAL | C4: 11695770 | D4: PROMOTORA SANDVILLE
A5: G2 | B5: GASTO OPERACIONAL COMERCIAL | C5: 25986435 | D5: PROMOTORA WESTVILLE
A6: Expr1 | B6: Expr2 | C6: SumaDeSumaDeVALOR | D6: EMPRESA
A7: G3 | B7: COMISIONES COMERCIAL | C7: 38797886 | D7: PROMOTORA SANDVILLE
A8: G3 | B8: COMISIONES COMERCIAL | C8: 18653528 | D8: PROMOTORA WESTVILLE
A9: G3 | B9: COMISIONES COMERCIAL | C9: 2626862 | D9: PROMOTORA SANDVILLE
A10: G3 | B10: COMISIONES COMERCIAL | C10: 1464536 | D10: PROMOTORA WESTVILLE
A11: Expr1 | B11: Expr2 | C11: SumaDeSumaDeVALOR | D11: EMPRESA
A12: G4 | B12: NOMINA ADMINISTRACION | C12: 38812609 | D12: PROMOTORA SANDVILLE
A13: G4 | B13: NOMINA ADMINISTRACION | C13: 5264662 | D13: PROMOTORA WESTVILLE
A14: Expr1 | B14: Expr2 | C14: SumaDeSumaDeVALOR | D14: EMPRESA
A15: G5 | B15: GASTO OPERACIONAL ADMINISTRACION | C15: 60780515 | D15: PROMOTORA SANDVILLE
A16: G5 | B16: GASTO OPERACIONAL ADMINISTRACION | C16: 13322861 | D16: PROMOTORA WESTVILLE
A17: G5 | B17: GASTO OPERACIONAL ADMINISTRACION | C17: 610251 | D17: STATUS COMERCIALIZADORA
A18: Expr1 | B18: Expr2 | C18: SumaDeSumaDeVALOR | D18: EMPRESA
A19: G6 | B19: NOMINA CARTERA | C19: 7163476 | D19: PROMOTORA SANDVILLE
A20: G6 | B20: NOMINA CARTERA | C20: 1995604 | D20: STATUS COMERCIALIZADORA
A21: Expr1 | B21: Expr2 | C21: SumaDeSumaDeVALOR | D21: EMPRESA
A22: G7 | B22: GASTO OPERACIONAL CARTERA | C22: 3143481 | D22: PROMOTORA SANDVILLE
A23: G7 | B23: GASTO OPERACIONAL CARTERA | C23: 1146460 | D23: PROMOTORA WESTVILLE
A24: Expr1 | B24: Expr2 | C24: SumaDeSumaDeVALOR | D24: EMPRESA
A25: G8 | B25: NOMINA PROYECTOS | C25: 22236026 | D25: QUADRATA CONSTRUCTORES
A26: Expr1 | B26: Expr2 | C26: SumaDeSumaDeVALOR | D26: EMPRESA
A27: G9 | B27: GASTO OPERACIONAL PROYECTOS | C27: 5972925 | D27: QUADRATA CONSTRUCTORES
A28: Expr1 | B28: Expr2 | C28: SumaDeSumaDeVALOR | D28: EMPRESA | E28: PROYECTO
A29: G10 | B29: GASTO OBRA CLUB | C29: 353000 | D29: QUADRATA CONSTRUCTORES | E29: SANDVILLE
A30: Expr1 | B30: Expr2 | C30: SumaDeSumaDeVALOR | D30: EMPRESA | E30: PROYECTO
A31: G11 | B31: GASTO OBRA CONDOMINIO | C31: 25317744 | D31: QUADRATA CONSTRUCTORES | E31: SANDVILLE BEACH
A32: Expr1 | B32: Expr2 | C32: SumaDeSumaDeVALOR | D32: EMPRESA | E32: PROYECTO
A33: G12 | B33: ANTICIPOS OBRA | C33: 127913653 | D33: QUADRATA CONSTRUCTORES | E33: SANDVILLE
A34: G12 | B34: ANTICIPOS OBRA | C34: 7850716 | D34: QUADRATA CONSTRUCTORES | E34: RANCHO MONTANA
A35: Expr1 | B35: Expr2 | C35: SumaDeSumaDeVALOR | D35: EMPRESA | E35: PROYECTO
A36: G13 | B36: NOMINA CARTERA | C36: 20000000 | D36: PROMOTORA SANDVILLE | E36: SANDVILLE BEACH
A37: G13 | B37: NOMINA CARTERA | C37: 6413084 | D37: PROMOTORA WESTVILLE | E37: WESTIVILLE
A38: G13 | B38: NOMINA CARTERA | C38: 50000000 | D38: QUADRATA CONSTRUCTORES | E38: RANCHO MONTANA

Sheet CONFIG
G1: ASINGACION DE % POR CC | H1: SANDVILLE BEACH | I1: SANDVILLE DEL MAR | J1: SANDVILLE DEL SOL | K1: MIRADOR DE WESTVILLE
B2: EMPRESA | G2: SALARIOS COMERCIALES | H2: 0 | I2: 0 | J2: 0 | K2: 1
A3: OFICINA | B3: SANDVILLE | C3: WESTVILLE | D3: STATUS | G3: GASTO OPERACIÓN COMERCIAL | H3: 0.5 | I3: 0.5
A4: MONTERIA | B4: 1 | G4: GASTO ADMINISTRATIVO | H4: 0.33 | I4: 0.33 | J4: 0.33
A5: MEDELLIN | B5: 2 | C5: 1 | D5: 1 | G5: GASTO ADMIN PROYECTOS | H5: 1 | I5: 0 | J5: 0 | K5: 0
A6: SINCELEJO | B6: 3 | G6: SALARIOS CARTERA | H6: 0.25 | I6: 0.25 | J6: 0.25 | K6: 0.25

Sheet GastosHistorico
A1: Fecha | B1: Comprobante | C1: Cuenta | D1: Descripcion Cuenta | E1: Tercero | F1: Descripcion Gasto | G1: Item | H1: Valor | I1: Empresa

Sheet Control
A1: Sandville Beach | B1: 0 | C1: 0 | D1: 0 | F1: % Ventas Total | G1: =+'RESULTADOS MES'!E8 -> 0 | H1: =+'RESULTADOS MES'!I8 -> 0
A2: Sandville del Mar | B2: 0 | C2: 0 | D2: 0 | F2: % Ventas Procesables | G2: =+'RESULTADOS MES'!E5 -> 0 | H2: =+'RESULTADOS MES'!I5 -> 0
A3: Sandville del Sol | B3: 0 | C3: 0 | D3: 0 | F3: % Recaudo Ventas | G3: =+'RESULTADOS MES'!E12 -> 0 | H3: =+'RESULTADOS MES'!I12 -> 0
A4: Tesoro Escondido | B4: 20 | C4: 0.1 | D4: 0.1 | F4: % Recaudo Comercial | G4: =+'RESULTADOS MES'!D36 -> 0 | H4: =+'RESULTADOS MES'!J36 -> 0
A5: Vegas de Venecia | B5: 17 | C5: 0.1 | D5: 0.05 | F5: % Recaudo Administrativo | G5: =+'RESULTADOS MES'!D51 -> 0 | H5: =+'RESULTADOS MES'!J51 -> 0
F6: % Recaudo Cartera | G6: =+G4+G5 -> 0 | H6: =+H4+H5 -> 0
F7: % Recaudo Total | G7: =+G3+G6 -> 0 | H7: =+H3+H6 -> 0
F8: % Presupuestado
